{"data": [{"frame_index": 1, "skeleton": []}, {"frame_index": 2, "skeleton": []}, {"frame_index": 3, "skeleton": []}, {"frame_index": 4, "skeleton": []}, {"frame_index": 5, "skeleton": []}, {"frame_index": 6, "skeleton": []}, {"frame_index": 7, "skeleton": []}, {"frame_index": 8, "skeleton": []}, {"frame_index": 9, "skeleton": []}, {"frame_index": 10, "skeleton": []}, {"frame_index": 11, "skeleton": []}, {"frame_index": 12, "skeleton": []}, {"frame_index": 13, "skeleton": []}, {"frame_index": 14, "skeleton": []}, {"frame_index": 15, "skeleton": []}, {"frame_index": 16, "skeleton": []}, {"frame_index": 17, "skeleton": []}, {"frame_index": 18, "skeleton": []}, {"frame_index": 19, "skeleton": []}, {"frame_index": 20, "skeleton": []}, {"frame_index": 21, "skeleton": []}, {"frame_index": 22, "skeleton": []}, {"frame_index": 23, "skeleton": []}, {"frame_index": 24, "skeleton": []}, {"frame_index": 25, "skeleton": []}, {"frame_index": 26, "skeleton": []}, {"frame_index": 27, "skeleton": []}, {"frame_index": 28, "skeleton": []}, {"frame_index": 29, "skeleton": []}, {"frame_index": 30, "skeleton": []}, {"frame_index": 31, "skeleton": []}, {"frame_index": 32, "skeleton": []}, {"frame_index": 33, "skeleton": []}, {"frame_index": 34, "skeleton": []}, {"frame_index": 35, "skeleton": []}, {"frame_index": 36, "skeleton": []}, {"frame_index": 37, "skeleton": []}, {"frame_index": 38, "skeleton": []}, {"frame_index": 39, "skeleton": []}, {"frame_index": 40, "skeleton": []}, {"frame_index": 41, "skeleton": []}, {"frame_index": 42, "skeleton": []}, {"frame_index": 43, "skeleton": []}, {"frame_index": 44, "skeleton": []}, {"frame_index": 45, "skeleton": []}, {"frame_index": 46, "skeleton": [{"pose": [0.000, 0.000, 0.311, 0.435, 0.368, 0.429, 0.000, 0.000, 0.000, 0.000, 0.243, 0.440, 0.186, 0.644, 0.000, 0.000, 0.383, 0.701, 0.000, 0.000, 0.000, 0.000, 0.288, 0.717, 0.000, 0.000, 0.000, 0.000, 0.000, 0.000, 0.000, 0.000, 0.000, 0.000, 0.000, 0.000], "score": [0.000, 0.317, 0.216, 0.000, 0.000, 0.294, 0.246, 0.000, 0.181, 0.000, 0.000, 0.123, 0.000, 0.000, 0.000, 0.000, 0.000, 0.000]}]}, {"frame_index": 47, "skeleton": []}, {"frame_index": 48, "skeleton": []}, {"frame_index": 49, "skeleton": []}, {"frame_index": 50, "skeleton": []}, {"frame_index": 51, "skeleton": []}, {"frame_index": 52, "skeleton": []}, {"frame_index": 53, "skeleton": []}, {"frame_index": 54, "skeleton": []}, {"frame_index": 55, "skeleton": []}, {"frame_index": 56, "skeleton": []}, {"frame_index": 57, "skeleton": []}, {"frame_index": 58, "skeleton": []}, {"frame_index": 59, "skeleton": []}, {"frame_index": 60, "skeleton": []}, {"frame_index": 61, "skeleton": []}, {"frame_index": 62, "skeleton": []}, {"frame_index": 63, "skeleton": []}, {"frame_index": 64, "skeleton": []}, {"frame_index": 65, "skeleton": []}, {"frame_index": 66, "skeleton": []}, {"frame_index": 67, "skeleton": []}, {"frame_index": 68, "skeleton": []}, {"frame_index": 69, "skeleton": []}, {"frame_index": 70, "skeleton": []}, {"frame_index": 71, "skeleton": []}, {"frame_index": 72, "skeleton": []}, {"frame_index": 73, "skeleton": [{"pose": [0.313, 0.122, 0.000, 0.000, 0.000, 0.000, 0.000, 0.000, 0.000, 0.000, 0.000, 0.000, 0.000, 0.000, 0.000, 0.000, 0.000, 0.000, 0.000, 0.000, 0.000, 0.000, 0.000, 0.000, 0.000, 0.000, 0.000, 0.000, 0.286, 0.052, 0.344, 0.092, 0.000, 0.000, 0.000, 0.000], "score": [0.467, 0.000, 0.000, 0.000, 0.000, 0.000, 0.000, 0.000, 0.000, 0.000, 0.000, 0.000, 0.000, 0.000, 0.472, 0.193, 0.000, 0.000]}]}, {"frame_index": 74, "skeleton": []}, {"frame_index": 75, "skeleton": [{"pose": [0.317, 0.152, 0.000, 0.000, 0.000, 0.000, 0.000, 0.000, 0.000, 0.000, 0.000, 0.000, 0.000, 0.000, 0.000, 0.000, 0.000, 0.000, 0.000, 0.000, 0.000, 0.000, 0.000, 0.000, 0.000, 0.000, 0.000, 0.000, 0.297, 0.076, 0.348, 0.117, 0.000, 0.000, 0.000, 0.000], "score": [0.470, 0.000, 0.000, 0.000, 0.000, 0.000, 0.000, 0.000, 0.000, 0.000, 0.000, 0.000, 0.000, 0.000, 0.489, 0.098, 0.000, 0.000]}]}, {"frame_index": 76, "skeleton": []}, {"frame_index": 77, "skeleton": []}, {"frame_index": 78, "skeleton": []}, {"frame_index": 79, "skeleton": [{"pose": [0.000, 0.000, 0.499, 0.280, 0.544, 0.291, 0.548, 0.383, 0.000, 0.000, 0.460, 0.272, 0.000, 0.000, 0.000, 0.000, 0.503, 0.476, 0.000, 0.000, 0.000, 0.000, 0.436, 0.459, 0.000, 0.000, 0.000, 0.000, 0.000, 0.000, 0.000, 0.000, 0.522, 0.212, 0.481, 0.209], "score": [0.000, 0.491, 0.503, 0.172, 0.000, 0.423, 0.000, 0.000, 0.236, 0.000, 0.000, 0.170, 0.000, 0.000, 0.000, 0.000, 0.400, 0.266]}]}, {"frame_index": 80, "skeleton": [{"pose": [0.000, 0.000, 0.497, 0.299, 0.540, 0.310, 0.548, 0.399, 0.532, 0.465, 0.456, 0.291, 0.000, 0.000, 0.000, 0.000, 0.501, 0.484, 0.000, 0.000, 0.000, 0.000, 0.436, 0.462, 0.000, 0.000, 0.000, 0.000, 0.000, 0.000, 0.000, 0.000, 0.518, 0.231, 0.479, 0.228], "score": [0.000, 0.646, 0.586, 0.205, 0.124, 0.524, 0.000, 0.000, 0.327, 0.000, 0.000, 0.273, 0.000, 0.000, 0.000, 0.000, 0.523, 0.428]}]}, {"frame_index": 81, "skeleton": [{"pose": [0.000, 0.000, 0.495, 0.321, 0.532, 0.329, 0.546, 0.408, 0.000, 0.000, 0.454, 0.315, 0.000, 0.000, 0.000, 0.000, 0.507, 0.495, 0.000, 0.000, 0.000, 0.000, 0.446, 0.481, 0.000, 0.000, 0.000, 0.000, 0.000, 0.000, 0.000, 0.000, 0.513, 0.250, 0.469, 0.250], "score": [0.000, 0.713, 0.669, 0.173, 0.000, 0.595, 0.000, 0.000, 0.411, 0.000, 0.000, 0.374, 0.000, 0.000, 0.000, 0.000, 0.640, 0.510]}]}, {"frame_index": 82, "skeleton": [{"pose": [0.000, 0.000, 0.483, 0.340, 0.524, 0.351, 0.000, 0.000, 0.000, 0.000, 0.446, 0.337, 0.000, 0.000, 0.000, 0.000, 0.513, 0.530, 0.000, 0.000, 0.000, 0.000, 0.444, 0.516, 0.000, 0.000, 0.000, 0.000, 0.000, 0.000, 0.000, 0.000, 0.505, 0.269, 0.466, 0.269], "score": [0.000, 0.417, 0.421, 0.000, 0.000, 0.235, 0.000, 0.000, 0.110, 0.000, 0.000, 0.065, 0.000, 0.000, 0.000, 0.000, 0.542, 0.299]}]}, {"frame_index": 83, "skeleton": [{"pose": [0.000, 0.000, 0.483, 0.359, 0.516, 0.367, 0.000, 0.000, 0.000, 0.000, 0.456, 0.359, 0.000, 0.000, 0.000, 0.000, 0.000, 0.000, 0.000, 0.000, 0.000, 0.000, 0.000, 0.000, 0.000, 0.000, 0.000, 0.000, 0.000, 0.000, 0.000, 0.000, 0.501, 0.291, 0.465, 0.291], "score": [0.000, 0.309, 0.338, 0.000, 0.000, 0.176, 0.000, 0.000, 0.000, 0.000, 0.000, 0.000, 0.000, 0.000, 0.000, 0.000, 0.388, 0.260]}]}, {"frame_index": 84, "skeleton": []}, {"frame_index": 85, "skeleton": []}, {"frame_index": 86, "skeleton": [{"pose": [0.000, 0.000, 0.456, 0.443, 0.477, 0.443, 0.000, 0.000, 0.000, 0.000, 0.442, 0.446, 0.000, 0.000, 0.000, 0.000, 0.000, 0.000, 0.000, 0.000, 0.000, 0.000, 0.000, 0.000, 0.000, 0.000, 0.000, 0.000, 0.000, 0.000, 0.000, 0.000, 0.485, 0.375, 0.450, 0.364], "score": [0.000, 0.255, 0.346, 0.000, 0.000, 0.176, 0.000, 0.000, 0.000, 0.000, 0.000, 0.000, 0.000, 0.000, 0.000, 0.000, 0.336, 0.171]}]}, {"frame_index": 87, "skeleton": []}, {"frame_index": 88, "skeleton": []}, {"frame_index": 89, "skeleton": []}, {"frame_index": 90, "skeleton": []}, {"frame_index": 91, "skeleton": []}, {"frame_index": 92, "skeleton": [{"pose": [0.000, 0.000, 0.207, 0.119, 0.196, 0.117, 0.278, 0.272, 0.354, 0.291, 0.000, 0.000, 0.000, 0.000, 0.000, 0.000, 0.000, 0.000, 0.000, 0.000, 0.000, 0.000, 0.000, 0.000, 0.000, 0.000, 0.000, 0.000, 0.000, 0.000, 0.000, 0.000, 0.291, 0.022, 0.000, 0.000], "score": [0.000, 0.122, 0.269, 0.210, 0.451, 0.000, 0.000, 0.000, 0.000, 0.000, 0.000, 0.000, 0.000, 0.000, 0.000, 0.000, 0.387, 0.000]}]}, {"frame_index": 93, "skeleton": [{"pose": [0.000, 0.000, 0.209, 0.185, 0.196, 0.185, 0.282, 0.337, 0.358, 0.356, 0.000, 0.000, 0.000, 0.000, 0.000, 0.000, 0.000, 0.000, 0.000, 0.000, 0.000, 0.000, 0.000, 0.000, 0.000, 0.000, 0.000, 0.000, 0.000, 0.000, 0.000, 0.000, 0.329, 0.054, 0.000, 0.000], "score": [0.000, 0.091, 0.222, 0.206, 0.336, 0.000, 0.000, 0.000, 0.000, 0.000, 0.000, 0.000, 0.000, 0.000, 0.000, 0.000, 0.532, 0.000]}]}, {"frame_index": 94, "skeleton": []}, {"frame_index": 95, "skeleton": [{"pose": [0.000, 0.000, 0.231, 0.321, 0.219, 0.323, 0.301, 0.495, 0.393, 0.511, 0.000, 0.000, 0.000, 0.000, 0.000, 0.000, 0.000, 0.000, 0.000, 0.000, 0.000, 0.000, 0.000, 0.000, 0.000, 0.000, 0.000, 0.000, 0.000, 0.000, 0.000, 0.000, 0.350, 0.215, 0.000, 0.000], "score": [0.000, 0.173, 0.266, 0.320, 0.218, 0.000, 0.000, 0.000, 0.000, 0.000, 0.000, 0.000, 0.000, 0.000, 0.000, 0.000, 0.590, 0.000]}]}, {"frame_index": 96, "skeleton": [{"pose": [0.000, 0.000, 0.252, 0.380, 0.237, 0.399, 0.305, 0.573, 0.417, 0.592, 0.260, 0.367, 0.000, 0.000, 0.000, 0.000, 0.237, 0.704, 0.000, 0.000, 0.000, 0.000, 0.000, 0.000, 0.000, 0.000, 0.000, 0.000, 0.000, 0.000, 0.000, 0.000, 0.350, 0.310, 0.000, 0.000], "score": [0.000, 0.291, 0.413, 0.568, 0.322, 0.157, 0.000, 0.000, 0.113, 0.000, 0.000, 0.000, 0.000, 0.000, 0.000, 0.000, 0.494, 0.000]}]}, {"frame_index": 97, "skeleton": [{"pose": [0.000, 0.000, 0.252, 0.462, 0.250, 0.478, 0.299, 0.666, 0.000, 0.000, 0.241, 0.440, 0.000, 0.000, 0.000, 0.000, 0.235, 0.799, 0.000, 0.000, 0.000, 0.000, 0.188, 0.774, 0.000, 0.000, 0.000, 0.000, 0.000, 0.000, 0.000, 0.000, 0.364, 0.383, 0.000, 0.000], "score": [0.000, 0.343, 0.348, 0.267, 0.000, 0.209, 0.000, 0.000, 0.119, 0.000, 0.000, 0.064, 0.000, 0.000, 0.000, 0.000, 0.520, 0.000]}]}, {"frame_index": 98, "skeleton": [{"pose": [0.000, 0.000, 0.270, 0.527, 0.266, 0.538, 0.297, 0.742, 0.000, 0.000, 0.270, 0.505, 0.000, 0.000, 0.000, 0.000, 0.000, 0.000, 0.000, 0.000, 0.000, 0.000, 0.000, 0.000, 0.000, 0.000, 0.000, 0.000, 0.000, 0.000, 0.000, 0.000, 0.372, 0.446, 0.000, 0.000], "score": [0.000, 0.262, 0.338, 0.267, 0.000, 0.144, 0.000, 0.000, 0.000, 0.000, 0.000, 0.000, 0.000, 0.000, 0.000, 0.000, 0.678, 0.000]}]}, {"frame_index": 99, "skeleton": [{"pose": [0.000, 0.000, 0.272, 0.571, 0.276, 0.579, 0.299, 0.758, 0.000, 0.000, 0.258, 0.546, 0.000, 0.000, 0.000, 0.000, 0.000, 0.000, 0.000, 0.000, 0.000, 0.000, 0.000, 0.000, 0.000, 0.000, 0.000, 0.000, 0.000, 0.000, 0.000, 0.000, 0.385, 0.503, 0.000, 0.000], "score": [0.000, 0.201, 0.185, 0.146, 0.000, 0.120, 0.000, 0.000, 0.000, 0.000, 0.000, 0.000, 0.000, 0.000, 0.000, 0.000, 0.566, 0.000]}]}, {"frame_index": 100, "skeleton": [{"pose": [0.000, 0.000, 0.305, 0.598, 0.280, 0.598, 0.299, 0.802, 0.309, 0.633, 0.000, 0.000, 0.000, 0.000, 0.000, 0.000, 0.000, 0.000, 0.000, 0.000, 0.000, 0.000, 0.000, 0.000, 0.000, 0.000, 0.000, 0.000, 0.000, 0.000, 0.000, 0.000, 0.393, 0.535, 0.000, 0.000], "score": [0.000, 0.063, 0.223, 0.335, 0.084, 0.000, 0.000, 0.000, 0.000, 0.000, 0.000, 0.000, 0.000, 0.000, 0.000, 0.000, 0.529, 0.000]}]}, {"frame_index": 101, "skeleton": [{"pose": [0.000, 0.000, 0.303, 0.620, 0.299, 0.622, 0.305, 0.813, 0.000, 0.000, 0.000, 0.000, 0.000, 0.000, 0.000, 0.000, 0.000, 0.000, 0.000, 0.000, 0.000, 0.000, 0.000, 0.000, 0.000, 0.000, 0.000, 0.000, 0.000, 0.000, 0.000, 0.000, 0.385, 0.557, 0.000, 0.000], "score": [0.000, 0.120, 0.216, 0.353, 0.000, 0.000, 0.000, 0.000, 0.000, 0.000, 0.000, 0.000, 0.000, 0.000, 0.000, 0.000, 0.571, 0.000]}]}, {"frame_index": 102, "skeleton": []}, {"frame_index": 103, "skeleton": []}, {"frame_index": 104, "skeleton": []}, {"frame_index": 105, "skeleton": []}, {"frame_index": 106, "skeleton": []}, {"frame_index": 107, "skeleton": []}, {"frame_index": 108, "skeleton": []}, {"frame_index": 109, "skeleton": []}, {"frame_index": 110, "skeleton": []}, {"frame_index": 111, "skeleton": []}, {"frame_index": 112, "skeleton": []}, {"frame_index": 113, "skeleton": []}, {"frame_index": 114, "skeleton": []}, {"frame_index": 115, "skeleton": [{"pose": [0.000, 0.000, 0.000, 0.000, 0.000, 0.000, 0.000, 0.000, 0.000, 0.000, 0.231, 0.008, 0.333, 0.120, 0.448, 0.285, 0.000, 0.000, 0.000, 0.000, 0.000, 0.000, 0.000, 0.000, 0.000, 0.000, 0.000, 0.000, 0.000, 0.000, 0.000, 0.000, 0.000, 0.000, 0.000, 0.000], "score": [0.000, 0.000, 0.000, 0.000, 0.000, 0.051, 0.294, 0.436, 0.000, 0.000, 0.000, 0.000, 0.000, 0.000, 0.000, 0.000, 0.000, 0.000]}]}, {"frame_index": 116, "skeleton": []}, {"frame_index": 117, "skeleton": []}, {"frame_index": 118, "skeleton": []}, {"frame_index": 119, "skeleton": []}, {"frame_index": 120, "skeleton": []}, {"frame_index": 121, "skeleton": []}, {"frame_index": 122, "skeleton": []}, {"frame_index": 123, "skeleton": []}, {"frame_index": 124, "skeleton": []}, {"frame_index": 125, "skeleton": []}, {"frame_index": 126, "skeleton": []}, {"frame_index": 127, "skeleton": []}, {"frame_index": 128, "skeleton": []}, {"frame_index": 129, "skeleton": []}, {"frame_index": 130, "skeleton": [{"pose": [0.000, 0.000, 0.403, 0.606, 0.532, 0.598, 0.000, 0.000, 0.000, 0.000, 0.284, 0.614, 0.186, 0.867, 0.000, 0.000, 0.495, 0.943, 0.000, 0.000, 0.000, 0.000, 0.362, 0.951, 0.000, 0.000, 0.000, 0.000, 0.000, 0.000, 0.000, 0.000, 0.464, 0.429, 0.321, 0.440], "score": [0.000, 0.446, 0.375, 0.000, 0.000, 0.446, 0.120, 0.000, 0.067, 0.000, 0.000, 0.064, 0.000, 0.000, 0.000, 0.000, 0.120, 0.125]}]}, {"frame_index": 131, "skeleton": [{"pose": [0.501, 0.573, 0.383, 0.666, 0.276, 0.617, 0.190, 0.861, 0.000, 0.000, 0.475, 0.712, 0.000, 0.000, 0.000, 0.000, 0.000, 0.000, 0.000, 0.000, 0.000, 0.000, 0.000, 0.000, 0.000, 0.000, 0.000, 0.000, 0.448, 0.505, 0.000, 0.000, 0.374, 0.505, 0.000, 0.000], "score": [0.096, 0.240, 0.361, 0.088, 0.000, 0.124, 0.000, 0.000, 0.000, 0.000, 0.000, 0.000, 0.000, 0.000, 0.200, 0.000, 0.138, 0.000]}]}, {"frame_index": 132, "skeleton": []}, {"frame_index": 133, "skeleton": []}, {"frame_index": 134, "skeleton": [{"pose": [0.354, 0.117, 0.000, 0.000, 0.000, 0.000, 0.000, 0.000, 0.000, 0.000, 0.000, 0.000, 0.000, 0.000, 0.000, 0.000, 0.000, 0.000, 0.000, 0.000, 0.000, 0.000, 0.000, 0.000, 0.000, 0.000, 0.000, 0.000, 0.315, 0.092, 0.354, 0.049, 0.000, 0.000, 0.000, 0.000], "score": [0.652, 0.000, 0.000, 0.000, 0.000, 0.000, 0.000, 0.000, 0.000, 0.000, 0.000, 0.000, 0.000, 0.000, 0.271, 0.592, 0.000, 0.000]}]}, {"frame_index": 135, "skeleton": [{"pose": [0.516, 0.587, 0.415, 0.655, 0.286, 0.617, 0.194, 0.883, 0.000, 0.000, 0.544, 0.682, 0.548, 0.916, 0.000, 0.000, 0.000, 0.000, 0.000, 0.000, 0.000, 0.000, 0.000, 0.000, 0.000, 0.000, 0.000, 0.000, 0.485, 0.535, 0.538, 0.554, 0.419, 0.503, 0.000, 0.000], "score": [0.189, 0.490, 0.435, 0.101, 0.000, 0.461, 0.101, 0.000, 0.000, 0.000, 0.000, 0.000, 0.000, 0.000, 0.240, 0.216, 0.294, 0.000]}]}, {"frame_index": 136, "skeleton": [{"pose": [0.000, 0.000, 0.413, 0.655, 0.536, 0.698, 0.546, 0.916, 0.000, 0.000, 0.276, 0.617, 0.190, 0.897, 0.000, 0.000, 0.000, 0.000, 0.000, 0.000, 0.000, 0.000, 0.000, 0.000, 0.000, 0.000, 0.000, 0.000, 0.000, 0.000, 0.000, 0.000, 0.518, 0.565, 0.000, 0.000], "score": [0.000, 0.400, 0.430, 0.073, 0.000, 0.417, 0.072, 0.000, 0.000, 0.000, 0.000, 0.000, 0.000, 0.000, 0.000, 0.000, 0.250, 0.000]}]}, {"frame_index": 137, "skeleton": []}, {"frame_index": 138, "skeleton": []}, {"frame_index": 139, "skeleton": []}, {"frame_index": 140, "skeleton": []}, {"frame_index": 141, "skeleton": []}, {"frame_index": 142, "skeleton": [{"pose": [0.000, 0.000, 0.000, 0.000, 0.000, 0.000, 0.000, 0.000, 0.000, 0.000, 0.207, 0.285, 0.284, 0.383, 0.346, 0.416, 0.000, 0.000, 0.000, 0.000, 0.000, 0.000, 0.000, 0.000, 0.000, 0.000, 0.000, 0.000, 0.000, 0.000, 0.000, 0.000, 0.000, 0.000, 0.000, 0.000], "score": [0.000, 0.000, 0.000, 0.000, 0.000, 0.261, 0.163, 0.426, 0.000, 0.000, 0.000, 0.000, 0.000, 0.000, 0.000, 0.000, 0.000, 0.000]}]}, {"frame_index": 143, "skeleton": []}, {"frame_index": 144, "skeleton": []}, {"frame_index": 145, "skeleton": [{"pose": [0.000, 0.000, 0.039, 0.291, 0.155, 0.272, 0.237, 0.438, 0.000, 0.000, 0.000, 0.000, 0.000, 0.000, 0.000, 0.000, 0.000, 0.000, 0.000, 0.000, 0.000, 0.000, 0.000, 0.000, 0.000, 0.000, 0.000, 0.000, 0.000, 0.000, 0.000, 0.000, 0.057, 0.147, 0.000, 0.000], "score": [0.000, 0.302, 0.474, 0.079, 0.000, 0.000, 0.000, 0.000, 0.000, 0.000, 0.000, 0.000, 0.000, 0.000, 0.000, 0.000, 0.146, 0.000]}]}, {"frame_index": 146, "skeleton": [{"pose": [0.000, 0.000, 0.016, 0.291, 0.000, 0.000, 0.000, 0.000, 0.000, 0.000, 0.123, 0.274, 0.219, 0.402, 0.000, 0.000, 0.000, 0.000, 0.000, 0.000, 0.000, 0.000, 0.000, 0.000, 0.000, 0.000, 0.000, 0.000, 0.000, 0.000, 0.000, 0.000, 0.000, 0.000, 0.000, 0.000], "score": [0.000, 0.315, 0.000, 0.000, 0.000, 0.401, 0.062, 0.000, 0.000, 0.000, 0.000, 0.000, 0.000, 0.000, 0.000, 0.000, 0.000, 0.000]}]}, {"frame_index": 147, "skeleton": []}, {"frame_index": 148, "skeleton": []}, {"frame_index": 149, "skeleton": []}, {"frame_index": 150, "skeleton": []}, {"frame_index": 151, "skeleton": []}, {"frame_index": 152, "skeleton": []}, {"frame_index": 153, "skeleton": []}, {"frame_index": 154, "skeleton": []}, {"frame_index": 155, "skeleton": []}, {"frame_index": 156, "skeleton": []}, {"frame_index": 157, "skeleton": []}, {"frame_index": 158, "skeleton": []}, {"frame_index": 159, "skeleton": []}, {"frame_index": 160, "skeleton": []}, {"frame_index": 161, "skeleton": []}, {"frame_index": 162, "skeleton": []}, {"frame_index": 163, "skeleton": []}, {"frame_index": 164, "skeleton": []}, {"frame_index": 165, "skeleton": []}, {"frame_index": 166, "skeleton": []}, {"frame_index": 167, "skeleton": []}, {"frame_index": 168, "skeleton": []}, {"frame_index": 169, "skeleton": []}, {"frame_index": 170, "skeleton": []}, {"frame_index": 171, "skeleton": []}, {"frame_index": 172, "skeleton": []}, {"frame_index": 173, "skeleton": []}, {"frame_index": 174, "skeleton": []}, {"frame_index": 175, "skeleton": []}, {"frame_index": 176, "skeleton": []}, {"frame_index": 177, "skeleton": []}, {"frame_index": 178, "skeleton": []}, {"frame_index": 179, "skeleton": []}, {"frame_index": 180, "skeleton": []}, {"frame_index": 181, "skeleton": []}, {"frame_index": 182, "skeleton": []}, {"frame_index": 183, "skeleton": []}, {"frame_index": 184, "skeleton": []}, {"frame_index": 185, "skeleton": []}, {"frame_index": 186, "skeleton": []}, {"frame_index": 187, "skeleton": []}, {"frame_index": 188, "skeleton": []}, {"frame_index": 189, "skeleton": []}, {"frame_index": 190, "skeleton": []}, {"frame_index": 191, "skeleton": []}, {"frame_index": 192, "skeleton": []}, {"frame_index": 193, "skeleton": []}, {"frame_index": 194, "skeleton": []}, {"frame_index": 195, "skeleton": []}, {"frame_index": 196, "skeleton": []}, {"frame_index": 197, "skeleton": []}, {"frame_index": 198, "skeleton": []}, {"frame_index": 199, "skeleton": []}, {"frame_index": 200, "skeleton": []}, {"frame_index": 201, "skeleton": []}, {"frame_index": 202, "skeleton": []}, {"frame_index": 203, "skeleton": []}, {"frame_index": 204, "skeleton": []}, {"frame_index": 205, "skeleton": []}, {"frame_index": 206, "skeleton": []}, {"frame_index": 207, "skeleton": []}, {"frame_index": 208, "skeleton": []}, {"frame_index": 209, "skeleton": []}, {"frame_index": 210, "skeleton": [{"pose": [0.000, 0.000, 0.000, 0.000, 0.000, 0.000, 0.000, 0.000, 0.000, 0.000, 0.088, 0.008, 0.184, 0.160, 0.284, 0.261, 0.000, 0.000, 0.000, 0.000, 0.000, 0.000, 0.000, 0.000, 0.000, 0.000, 0.000, 0.000, 0.000, 0.000, 0.000, 0.000, 0.000, 0.000, 0.000, 0.000], "score": [0.000, 0.000, 0.000, 0.000, 0.000, 0.090, 0.184, 0.485, 0.000, 0.000, 0.000, 0.000, 0.000, 0.000, 0.000, 0.000, 0.000, 0.000]}]}, {"frame_index": 211, "skeleton": [{"pose": [0.000, 0.000, 0.000, 0.000, 0.000, 0.000, 0.000, 0.000, 0.000, 0.000, 0.088, 0.008, 0.170, 0.141, 0.291, 0.285, 0.000, 0.000, 0.000, 0.000, 0.000, 0.000, 0.000, 0.000, 0.000, 0.000, 0.000, 0.000, 0.000, 0.000, 0.000, 0.000, 0.000, 0.000, 0.000, 0.000], "score": [0.000, 0.000, 0.000, 0.000, 0.000, 0.069, 0.267, 0.460, 0.000, 0.000, 0.000, 0.000, 0.000, 0.000, 0.000, 0.000, 0.000, 0.000]}]}, {"frame_index": 212, "skeleton": [{"pose": [0.000, 0.000, 0.000, 0.000, 0.000, 0.000, 0.000, 0.000, 0.000, 0.000, 0.102, 0.008, 0.168, 0.141, 0.293, 0.304, 0.000, 0.000, 0.000, 0.000, 0.000, 0.000, 0.000, 0.000, 0.000, 0.000, 0.000, 0.000, 0.000, 0.000, 0.000, 0.000, 0.000, 0.000, 0.000, 0.000], "score": [0.000, 0.000, 0.000, 0.000, 0.000, 0.071, 0.278, 0.475, 0.000, 0.000, 0.000, 0.000, 0.000, 0.000, 0.000, 0.000, 0.000, 0.000]}]}, {"frame_index": 213, "skeleton": [{"pose": [0.000, 0.000, 0.000, 0.000, 0.000, 0.000, 0.000, 0.000, 0.000, 0.000, 0.106, 0.008, 0.184, 0.163, 0.291, 0.304, 0.000, 0.000, 0.000, 0.000, 0.000, 0.000, 0.000, 0.000, 0.000, 0.000, 0.000, 0.000, 0.000, 0.000, 0.000, 0.000, 0.000, 0.000, 0.000, 0.000], "score": [0.000, 0.000, 0.000, 0.000, 0.000, 0.126, 0.293, 0.478, 0.000, 0.000, 0.000, 0.000, 0.000, 0.000, 0.000, 0.000, 0.000, 0.000]}]}, {"frame_index": 214, "skeleton": [{"pose": [0.000, 0.000, 0.000, 0.000, 0.000, 0.000, 0.000, 0.000, 0.000, 0.000, 0.104, 0.008, 0.178, 0.152, 0.295, 0.302, 0.000, 0.000, 0.000, 0.000, 0.000, 0.000, 0.000, 0.000, 0.000, 0.000, 0.000, 0.000, 0.000, 0.000, 0.000, 0.000, 0.000, 0.000, 0.000, 0.000], "score": [0.000, 0.000, 0.000, 0.000, 0.000, 0.086, 0.308, 0.476, 0.000, 0.000, 0.000, 0.000, 0.000, 0.000, 0.000, 0.000, 0.000, 0.000]}]}, {"frame_index": 215, "skeleton": [{"pose": [0.000, 0.000, 0.000, 0.000, 0.000, 0.000, 0.000, 0.000, 0.000, 0.000, 0.121, 0.008, 0.176, 0.158, 0.299, 0.299, 0.000, 0.000, 0.000, 0.000, 0.000, 0.000, 0.000, 0.000, 0.000, 0.000, 0.000, 0.000, 0.000, 0.000, 0.000, 0.000, 0.000, 0.000, 0.000, 0.000], "score": [0.000, 0.000, 0.000, 0.000, 0.000, 0.096, 0.266, 0.540, 0.000, 0.000, 0.000, 0.000, 0.000, 0.000, 0.000, 0.000, 0.000, 0.000]}]}, {"frame_index": 216, "skeleton": [{"pose": [0.000, 0.000, 0.000, 0.000, 0.000, 0.000, 0.000, 0.000, 0.000, 0.000, 0.123, 0.008, 0.188, 0.166, 0.301, 0.296, 0.000, 0.000, 0.000, 0.000, 0.000, 0.000, 0.000, 0.000, 0.000, 0.000, 0.000, 0.000, 0.000, 0.000, 0.000, 0.000, 0.000, 0.000, 0.000, 0.000], "score": [0.000, 0.000, 0.000, 0.000, 0.000, 0.111, 0.216, 0.523, 0.000, 0.000, 0.000, 0.000, 0.000, 0.000, 0.000, 0.000, 0.000, 0.000]}]}, {"frame_index": 217, "skeleton": [{"pose": [0.000, 0.000, 0.000, 0.000, 0.000, 0.000, 0.000, 0.000, 0.000, 0.000, 0.125, 0.008, 0.201, 0.182, 0.313, 0.296, 0.000, 0.000, 0.000, 0.000, 0.000, 0.000, 0.000, 0.000, 0.000, 0.000, 0.000, 0.000, 0.000, 0.000, 0.000, 0.000, 0.000, 0.000, 0.000, 0.000], "score": [0.000, 0.000, 0.000, 0.000, 0.000, 0.102, 0.266, 0.567, 0.000, 0.000, 0.000, 0.000, 0.000, 0.000, 0.000, 0.000, 0.000, 0.000]}]}, {"frame_index": 218, "skeleton": [{"pose": [0.000, 0.000, 0.000, 0.000, 0.000, 0.000, 0.000, 0.000, 0.000, 0.000, 0.129, 0.008, 0.207, 0.163, 0.317, 0.294, 0.000, 0.000, 0.000, 0.000, 0.000, 0.000, 0.000, 0.000, 0.000, 0.000, 0.000, 0.000, 0.000, 0.000, 0.000, 0.000, 0.000, 0.000, 0.000, 0.000], "score": [0.000, 0.000, 0.000, 0.000, 0.000, 0.106, 0.207, 0.608, 0.000, 0.000, 0.000, 0.000, 0.000, 0.000, 0.000, 0.000, 0.000, 0.000]}]}, {"frame_index": 219, "skeleton": [{"pose": [0.000, 0.000, 0.000, 0.000, 0.000, 0.000, 0.000, 0.000, 0.000, 0.000, 0.135, 0.008, 0.215, 0.160, 0.319, 0.294, 0.000, 0.000, 0.000, 0.000, 0.000, 0.000, 0.000, 0.000, 0.000, 0.000, 0.000, 0.000, 0.000, 0.000, 0.000, 0.000, 0.000, 0.000, 0.000, 0.000], "score": [0.000, 0.000, 0.000, 0.000, 0.000, 0.089, 0.217, 0.588, 0.000, 0.000, 0.000, 0.000, 0.000, 0.000, 0.000, 0.000, 0.000, 0.000]}]}, {"frame_index": 220, "skeleton": [{"pose": [0.000, 0.000, 0.000, 0.000, 0.000, 0.000, 0.000, 0.000, 0.000, 0.000, 0.137, 0.008, 0.221, 0.160, 0.325, 0.294, 0.000, 0.000, 0.000, 0.000, 0.000, 0.000, 0.000, 0.000, 0.000, 0.000, 0.000, 0.000, 0.000, 0.000, 0.000, 0.000, 0.000, 0.000, 0.000, 0.000], "score": [0.000, 0.000, 0.000, 0.000, 0.000, 0.083, 0.233, 0.576, 0.000, 0.000, 0.000, 0.000, 0.000, 0.000, 0.000, 0.000, 0.000, 0.000]}]}, {"frame_index": 221, "skeleton": [{"pose": [0.000, 0.000, 0.000, 0.000, 0.000, 0.000, 0.000, 0.000, 0.000, 0.000, 0.149, 0.008, 0.223, 0.160, 0.334, 0.294, 0.000, 0.000, 0.000, 0.000, 0.000, 0.000, 0.000, 0.000, 0.000, 0.000, 0.000, 0.000, 0.000, 0.000, 0.000, 0.000, 0.000, 0.000, 0.000, 0.000], "score": [0.000, 0.000, 0.000, 0.000, 0.000, 0.082, 0.296, 0.652, 0.000, 0.000, 0.000, 0.000, 0.000, 0.000, 0.000, 0.000, 0.000, 0.000]}]}, {"frame_index": 222, "skeleton": [{"pose": [0.000, 0.000, 0.000, 0.000, 0.000, 0.000, 0.000, 0.000, 0.000, 0.000, 0.149, 0.008, 0.235, 0.163, 0.336, 0.293, 0.000, 0.000, 0.000, 0.000, 0.000, 0.000, 0.000, 0.000, 0.000, 0.000, 0.000, 0.000, 0.000, 0.000, 0.000, 0.000, 0.000, 0.000, 0.000, 0.000], "score": [0.000, 0.000, 0.000, 0.000, 0.000, 0.077, 0.295, 0.638, 0.000, 0.000, 0.000, 0.000, 0.000, 0.000, 0.000, 0.000, 0.000, 0.000]}]}, {"frame_index": 223, "skeleton": [{"pose": [0.000, 0.000, 0.000, 0.000, 0.000, 0.000, 0.000, 0.000, 0.000, 0.000, 0.153, 0.008, 0.237, 0.160, 0.344, 0.293, 0.000, 0.000, 0.000, 0.000, 0.000, 0.000, 0.000, 0.000, 0.000, 0.000, 0.000, 0.000, 0.000, 0.000, 0.000, 0.000, 0.000, 0.000, 0.000, 0.000], "score": [0.000, 0.000, 0.000, 0.000, 0.000, 0.088, 0.288, 0.596, 0.000, 0.000, 0.000, 0.000, 0.000, 0.000, 0.000, 0.000, 0.000, 0.000]}]}, {"frame_index": 224, "skeleton": [{"pose": [0.000, 0.000, 0.000, 0.000, 0.000, 0.000, 0.000, 0.000, 0.000, 0.000, 0.151, 0.008, 0.231, 0.144, 0.346, 0.291, 0.000, 0.000, 0.000, 0.000, 0.000, 0.000, 0.000, 0.000, 0.000, 0.000, 0.000, 0.000, 0.000, 0.000, 0.000, 0.000, 0.000, 0.000, 0.000, 0.000], "score": [0.000, 0.000, 0.000, 0.000, 0.000, 0.075, 0.283, 0.630, 0.000, 0.000, 0.000, 0.000, 0.000, 0.000, 0.000, 0.000, 0.000, 0.000]}]}, {"frame_index": 225, "skeleton": [{"pose": [0.000, 0.000, 0.000, 0.000, 0.000, 0.000, 0.000, 0.000, 0.000, 0.000, 0.149, 0.008, 0.237, 0.158, 0.346, 0.291, 0.000, 0.000, 0.000, 0.000, 0.000, 0.000, 0.000, 0.000, 0.000, 0.000, 0.000, 0.000, 0.000, 0.000, 0.000, 0.000, 0.000, 0.000, 0.000, 0.000], "score": [0.000, 0.000, 0.000, 0.000, 0.000, 0.095, 0.281, 0.615, 0.000, 0.000, 0.000, 0.000, 0.000, 0.000, 0.000, 0.000, 0.000, 0.000]}]}, {"frame_index": 226, "skeleton": [{"pose": [0.000, 0.000, 0.000, 0.000, 0.000, 0.000, 0.000, 0.000, 0.000, 0.000, 0.143, 0.008, 0.221, 0.141, 0.346, 0.291, 0.000, 0.000, 0.000, 0.000, 0.000, 0.000, 0.000, 0.000, 0.000, 0.000, 0.000, 0.000, 0.000, 0.000, 0.000, 0.000, 0.000, 0.000, 0.000, 0.000], "score": [0.000, 0.000, 0.000, 0.000, 0.000, 0.070, 0.221, 0.607, 0.000, 0.000, 0.000, 0.000, 0.000, 0.000, 0.000, 0.000, 0.000, 0.000]}]}, {"frame_index": 227, "skeleton": [{"pose": [0.000, 0.000, 0.000, 0.000, 0.000, 0.000, 0.000, 0.000, 0.000, 0.000, 0.145, 0.008, 0.217, 0.141, 0.344, 0.293, 0.000, 0.000, 0.000, 0.000, 0.000, 0.000, 0.000, 0.000, 0.000, 0.000, 0.000, 0.000, 0.000, 0.000, 0.000, 0.000, 0.000, 0.000, 0.000, 0.000], "score": [0.000, 0.000, 0.000, 0.000, 0.000, 0.062, 0.220, 0.577, 0.000, 0.000, 0.000, 0.000, 0.000, 0.000, 0.000, 0.000, 0.000, 0.000]}]}, {"frame_index": 228, "skeleton": [{"pose": [0.000, 0.000, 0.000, 0.000, 0.000, 0.000, 0.000, 0.000, 0.000, 0.000, 0.143, 0.008, 0.211, 0.144, 0.338, 0.293, 0.000, 0.000, 0.000, 0.000, 0.000, 0.000, 0.000, 0.000, 0.000, 0.000, 0.000, 0.000, 0.000, 0.000, 0.000, 0.000, 0.000, 0.000, 0.000, 0.000], "score": [0.000, 0.000, 0.000, 0.000, 0.000, 0.062, 0.239, 0.611, 0.000, 0.000, 0.000, 0.000, 0.000, 0.000, 0.000, 0.000, 0.000, 0.000]}]}, {"frame_index": 229, "skeleton": [{"pose": [0.000, 0.000, 0.000, 0.000, 0.000, 0.000, 0.000, 0.000, 0.000, 0.000, 0.139, 0.008, 0.219, 0.158, 0.336, 0.294, 0.000, 0.000, 0.000, 0.000, 0.000, 0.000, 0.000, 0.000, 0.000, 0.000, 0.000, 0.000, 0.000, 0.000, 0.000, 0.000, 0.000, 0.000, 0.000, 0.000], "score": [0.000, 0.000, 0.000, 0.000, 0.000, 0.069, 0.241, 0.595, 0.000, 0.000, 0.000, 0.000, 0.000, 0.000, 0.000, 0.000, 0.000, 0.000]}]}, {"frame_index": 230, "skeleton": [{"pose": [0.000, 0.000, 0.000, 0.000, 0.000, 0.000, 0.000, 0.000, 0.000, 0.000, 0.139, 0.008, 0.213, 0.147, 0.333, 0.302, 0.000, 0.000, 0.000, 0.000, 0.000, 0.000, 0.000, 0.000, 0.000, 0.000, 0.000, 0.000, 0.000, 0.000, 0.000, 0.000, 0.000, 0.000, 0.000, 0.000], "score": [0.000, 0.000, 0.000, 0.000, 0.000, 0.076, 0.235, 0.548, 0.000, 0.000, 0.000, 0.000, 0.000, 0.000, 0.000, 0.000, 0.000, 0.000]}]}, {"frame_index": 231, "skeleton": [{"pose": [0.000, 0.000, 0.000, 0.000, 0.000, 0.000, 0.000, 0.000, 0.000, 0.000, 0.137, 0.008, 0.209, 0.160, 0.325, 0.307, 0.000, 0.000, 0.000, 0.000, 0.000, 0.000, 0.000, 0.000, 0.000, 0.000, 0.000, 0.000, 0.000, 0.000, 0.000, 0.000, 0.000, 0.000, 0.000, 0.000], "score": [0.000, 0.000, 0.000, 0.000, 0.000, 0.096, 0.172, 0.472, 0.000, 0.000, 0.000, 0.000, 0.000, 0.000, 0.000, 0.000, 0.000, 0.000]}]}, {"frame_index": 232, "skeleton": [{"pose": [0.000, 0.000, 0.000, 0.000, 0.000, 0.000, 0.000, 0.000, 0.000, 0.000, 0.131, 0.008, 0.203, 0.160, 0.317, 0.304, 0.000, 0.000, 0.000, 0.000, 0.000, 0.000, 0.000, 0.000, 0.000, 0.000, 0.000, 0.000, 0.000, 0.000, 0.000, 0.000, 0.000, 0.000, 0.000, 0.000], "score": [0.000, 0.000, 0.000, 0.000, 0.000, 0.095, 0.194, 0.494, 0.000, 0.000, 0.000, 0.000, 0.000, 0.000, 0.000, 0.000, 0.000, 0.000]}]}, {"frame_index": 233, "skeleton": [{"pose": [0.000, 0.000, 0.000, 0.000, 0.000, 0.000, 0.000, 0.000, 0.000, 0.000, 0.131, 0.008, 0.194, 0.168, 0.311, 0.310, 0.000, 0.000, 0.000, 0.000, 0.000, 0.000, 0.000, 0.000, 0.000, 0.000, 0.000, 0.000, 0.000, 0.000, 0.000, 0.000, 0.000, 0.000, 0.000, 0.000], "score": [0.000, 0.000, 0.000, 0.000, 0.000, 0.104, 0.249, 0.515, 0.000, 0.000, 0.000, 0.000, 0.000, 0.000, 0.000, 0.000, 0.000, 0.000]}]}, {"frame_index": 234, "skeleton": [{"pose": [0.000, 0.000, 0.000, 0.000, 0.000, 0.000, 0.000, 0.000, 0.000, 0.000, 0.123, 0.008, 0.184, 0.169, 0.303, 0.310, 0.000, 0.000, 0.000, 0.000, 0.000, 0.000, 0.000, 0.000, 0.000, 0.000, 0.000, 0.000, 0.000, 0.000, 0.000, 0.000, 0.000, 0.000, 0.000, 0.000], "score": [0.000, 0.000, 0.000, 0.000, 0.000, 0.086, 0.231, 0.518, 0.000, 0.000, 0.000, 0.000, 0.000, 0.000, 0.000, 0.000, 0.000, 0.000]}]}, {"frame_index": 235, "skeleton": [{"pose": [0.000, 0.000, 0.000, 0.000, 0.000, 0.000, 0.000, 0.000, 0.000, 0.000, 0.119, 0.008, 0.188, 0.163, 0.301, 0.310, 0.000, 0.000, 0.000, 0.000, 0.000, 0.000, 0.000, 0.000, 0.000, 0.000, 0.000, 0.000, 0.000, 0.000, 0.000, 0.000, 0.000, 0.000, 0.000, 0.000], "score": [0.000, 0.000, 0.000, 0.000, 0.000, 0.092, 0.243, 0.594, 0.000, 0.000, 0.000, 0.000, 0.000, 0.000, 0.000, 0.000, 0.000, 0.000]}]}, {"frame_index": 236, "skeleton": [{"pose": [0.000, 0.000, 0.000, 0.000, 0.000, 0.000, 0.000, 0.000, 0.000, 0.000, 0.111, 0.008, 0.188, 0.163, 0.301, 0.312, 0.000, 0.000, 0.000, 0.000, 0.000, 0.000, 0.000, 0.000, 0.000, 0.000, 0.000, 0.000, 0.000, 0.000, 0.000, 0.000, 0.000, 0.000, 0.000, 0.000], "score": [0.000, 0.000, 0.000, 0.000, 0.000, 0.098, 0.267, 0.602, 0.000, 0.000, 0.000, 0.000, 0.000, 0.000, 0.000, 0.000, 0.000, 0.000]}]}, {"frame_index": 237, "skeleton": [{"pose": [0.000, 0.000, 0.000, 0.000, 0.000, 0.000, 0.000, 0.000, 0.000, 0.000, 0.113, 0.008, 0.188, 0.174, 0.301, 0.310, 0.000, 0.000, 0.000, 0.000, 0.000, 0.000, 0.000, 0.000, 0.000, 0.000, 0.000, 0.000, 0.000, 0.000, 0.000, 0.000, 0.000, 0.000, 0.000, 0.000], "score": [0.000, 0.000, 0.000, 0.000, 0.000, 0.095, 0.270, 0.608, 0.000, 0.000, 0.000, 0.000, 0.000, 0.000, 0.000, 0.000, 0.000, 0.000]}]}, {"frame_index": 238, "skeleton": [{"pose": [0.000, 0.000, 0.000, 0.000, 0.000, 0.000, 0.000, 0.000, 0.000, 0.000, 0.106, 0.008, 0.190, 0.163, 0.301, 0.313, 0.000, 0.000, 0.000, 0.000, 0.000, 0.000, 0.000, 0.000, 0.000, 0.000, 0.000, 0.000, 0.000, 0.000, 0.000, 0.000, 0.000, 0.000, 0.000, 0.000], "score": [0.000, 0.000, 0.000, 0.000, 0.000, 0.097, 0.284, 0.593, 0.000, 0.000, 0.000, 0.000, 0.000, 0.000, 0.000, 0.000, 0.000, 0.000]}]}, {"frame_index": 239, "skeleton": [{"pose": [0.000, 0.000, 0.000, 0.000, 0.000, 0.000, 0.000, 0.000, 0.000, 0.000, 0.108, 0.008, 0.188, 0.174, 0.301, 0.315, 0.000, 0.000, 0.000, 0.000, 0.000, 0.000, 0.000, 0.000, 0.000, 0.000, 0.000, 0.000, 0.000, 0.000, 0.000, 0.000, 0.000, 0.000, 0.000, 0.000], "score": [0.000, 0.000, 0.000, 0.000, 0.000, 0.088, 0.265, 0.584, 0.000, 0.000, 0.000, 0.000, 0.000, 0.000, 0.000, 0.000, 0.000, 0.000]}]}, {"frame_index": 240, "skeleton": [{"pose": [0.000, 0.000, 0.000, 0.000, 0.000, 0.000, 0.000, 0.000, 0.000, 0.000, 0.117, 0.008, 0.188, 0.163, 0.301, 0.315, 0.000, 0.000, 0.000, 0.000, 0.000, 0.000, 0.000, 0.000, 0.000, 0.000, 0.000, 0.000, 0.000, 0.000, 0.000, 0.000, 0.000, 0.000, 0.000, 0.000], "score": [0.000, 0.000, 0.000, 0.000, 0.000, 0.110, 0.246, 0.570, 0.000, 0.000, 0.000, 0.000, 0.000, 0.000, 0.000, 0.000, 0.000, 0.000]}]}, {"frame_index": 241, "skeleton": [{"pose": [0.000, 0.000, 0.000, 0.000, 0.000, 0.000, 0.000, 0.000, 0.000, 0.000, 0.119, 0.008, 0.201, 0.182, 0.301, 0.312, 0.000, 0.000, 0.000, 0.000, 0.000, 0.000, 0.000, 0.000, 0.000, 0.000, 0.000, 0.000, 0.000, 0.000, 0.000, 0.000, 0.000, 0.000, 0.000, 0.000], "score": [0.000, 0.000, 0.000, 0.000, 0.000, 0.132, 0.266, 0.554, 0.000, 0.000, 0.000, 0.000, 0.000, 0.000, 0.000, 0.000, 0.000, 0.000]}]}, {"frame_index": 242, "skeleton": [{"pose": [0.000, 0.000, 0.000, 0.000, 0.000, 0.000, 0.000, 0.000, 0.000, 0.000, 0.117, 0.008, 0.198, 0.179, 0.303, 0.312, 0.000, 0.000, 0.000, 0.000, 0.000, 0.000, 0.000, 0.000, 0.000, 0.000, 0.000, 0.000, 0.000, 0.000, 0.000, 0.000, 0.000, 0.000, 0.000, 0.000], "score": [0.000, 0.000, 0.000, 0.000, 0.000, 0.127, 0.269, 0.606, 0.000, 0.000, 0.000, 0.000, 0.000, 0.000, 0.000, 0.000, 0.000, 0.000]}]}, {"frame_index": 243, "skeleton": [{"pose": [0.000, 0.000, 0.000, 0.000, 0.000, 0.000, 0.000, 0.000, 0.000, 0.000, 0.117, 0.008, 0.200, 0.182, 0.303, 0.312, 0.000, 0.000, 0.000, 0.000, 0.000, 0.000, 0.000, 0.000, 0.000, 0.000, 0.000, 0.000, 0.000, 0.000, 0.000, 0.000, 0.000, 0.000, 0.000, 0.000], "score": [0.000, 0.000, 0.000, 0.000, 0.000, 0.137, 0.272, 0.602, 0.000, 0.000, 0.000, 0.000, 0.000, 0.000, 0.000, 0.000, 0.000, 0.000]}]}, {"frame_index": 244, "skeleton": [{"pose": [0.000, 0.000, 0.000, 0.000, 0.000, 0.000, 0.000, 0.000, 0.000, 0.000, 0.115, 0.008, 0.196, 0.177, 0.303, 0.312, 0.000, 0.000, 0.000, 0.000, 0.000, 0.000, 0.000, 0.000, 0.000, 0.000, 0.000, 0.000, 0.000, 0.000, 0.000, 0.000, 0.000, 0.000, 0.000, 0.000], "score": [0.000, 0.000, 0.000, 0.000, 0.000, 0.109, 0.236, 0.575, 0.000, 0.000, 0.000, 0.000, 0.000, 0.000, 0.000, 0.000, 0.000, 0.000]}]}, {"frame_index": 245, "skeleton": [{"pose": [0.000, 0.000, 0.000, 0.000, 0.000, 0.000, 0.000, 0.000, 0.000, 0.000, 0.106, 0.008, 0.186, 0.163, 0.301, 0.304, 0.000, 0.000, 0.000, 0.000, 0.000, 0.000, 0.000, 0.000, 0.000, 0.000, 0.000, 0.000, 0.000, 0.000, 0.000, 0.000, 0.000, 0.000, 0.000, 0.000], "score": [0.000, 0.000, 0.000, 0.000, 0.000, 0.094, 0.284, 0.550, 0.000, 0.000, 0.000, 0.000, 0.000, 0.000, 0.000, 0.000, 0.000, 0.000]}]}, {"frame_index": 246, "skeleton": [{"pose": [0.000, 0.000, 0.000, 0.000, 0.000, 0.000, 0.000, 0.000, 0.000, 0.000, 0.110, 0.008, 0.198, 0.182, 0.303, 0.307, 0.000, 0.000, 0.000, 0.000, 0.000, 0.000, 0.000, 0.000, 0.000, 0.000, 0.000, 0.000, 0.000, 0.000, 0.000, 0.000, 0.000, 0.000, 0.000, 0.000], "score": [0.000, 0.000, 0.000, 0.000, 0.000, 0.092, 0.282, 0.546, 0.000, 0.000, 0.000, 0.000, 0.000, 0.000, 0.000, 0.000, 0.000, 0.000]}]}, {"frame_index": 247, "skeleton": [{"pose": [0.000, 0.000, 0.000, 0.000, 0.000, 0.000, 0.000, 0.000, 0.000, 0.000, 0.115, 0.008, 0.174, 0.155, 0.305, 0.310, 0.000, 0.000, 0.000, 0.000, 0.000, 0.000, 0.000, 0.000, 0.000, 0.000, 0.000, 0.000, 0.000, 0.000, 0.000, 0.000, 0.000, 0.000, 0.000, 0.000], "score": [0.000, 0.000, 0.000, 0.000, 0.000, 0.052, 0.231, 0.513, 0.000, 0.000, 0.000, 0.000, 0.000, 0.000, 0.000, 0.000, 0.000, 0.000]}]}, {"frame_index": 248, "skeleton": [{"pose": [0.000, 0.000, 0.000, 0.000, 0.000, 0.000, 0.000, 0.000, 0.000, 0.000, 0.110, 0.008, 0.180, 0.177, 0.309, 0.307, 0.000, 0.000, 0.000, 0.000, 0.000, 0.000, 0.000, 0.000, 0.000, 0.000, 0.000, 0.000, 0.000, 0.000, 0.000, 0.000, 0.000, 0.000, 0.000, 0.000], "score": [0.000, 0.000, 0.000, 0.000, 0.000, 0.061, 0.273, 0.441, 0.000, 0.000, 0.000, 0.000, 0.000, 0.000, 0.000, 0.000, 0.000, 0.000]}]}, {"frame_index": 249, "skeleton": [{"pose": [0.000, 0.000, 0.000, 0.000, 0.000, 0.000, 0.000, 0.000, 0.000, 0.000, 0.108, 0.008, 0.184, 0.179, 0.313, 0.312, 0.000, 0.000, 0.000, 0.000, 0.000, 0.000, 0.000, 0.000, 0.000, 0.000, 0.000, 0.000, 0.000, 0.000, 0.000, 0.000, 0.000, 0.000, 0.000, 0.000], "score": [0.000, 0.000, 0.000, 0.000, 0.000, 0.081, 0.276, 0.402, 0.000, 0.000, 0.000, 0.000, 0.000, 0.000, 0.000, 0.000, 0.000, 0.000]}]}, {"frame_index": 250, "skeleton": [{"pose": [0.000, 0.000, 0.000, 0.000, 0.000, 0.000, 0.000, 0.000, 0.000, 0.000, 0.110, 0.008, 0.172, 0.179, 0.311, 0.293, 0.000, 0.000, 0.000, 0.000, 0.000, 0.000, 0.000, 0.000, 0.000, 0.000, 0.000, 0.000, 0.000, 0.000, 0.000, 0.000, 0.000, 0.000, 0.000, 0.000], "score": [0.000, 0.000, 0.000, 0.000, 0.000, 0.072, 0.334, 0.568, 0.000, 0.000, 0.000, 0.000, 0.000, 0.000, 0.000, 0.000, 0.000, 0.000]}]}, {"frame_index": 251, "skeleton": [{"pose": [0.000, 0.000, 0.000, 0.000, 0.000, 0.000, 0.000, 0.000, 0.000, 0.000, 0.108, 0.008, 0.172, 0.177, 0.307, 0.288, 0.000, 0.000, 0.000, 0.000, 0.000, 0.000, 0.000, 0.000, 0.000, 0.000, 0.000, 0.000, 0.000, 0.000, 0.000, 0.000, 0.000, 0.000, 0.000, 0.000], "score": [0.000, 0.000, 0.000, 0.000, 0.000, 0.076, 0.365, 0.547, 0.000, 0.000, 0.000, 0.000, 0.000, 0.000, 0.000, 0.000, 0.000, 0.000]}]}, {"frame_index": 252, "skeleton": [{"pose": [0.000, 0.000, 0.000, 0.000, 0.000, 0.000, 0.000, 0.000, 0.000, 0.000, 0.108, 0.008, 0.174, 0.174, 0.309, 0.285, 0.000, 0.000, 0.000, 0.000, 0.000, 0.000, 0.000, 0.000, 0.000, 0.000, 0.000, 0.000, 0.000, 0.000, 0.000, 0.000, 0.000, 0.000, 0.000, 0.000], "score": [0.000, 0.000, 0.000, 0.000, 0.000, 0.073, 0.374, 0.551, 0.000, 0.000, 0.000, 0.000, 0.000, 0.000, 0.000, 0.000, 0.000, 0.000]}]}, {"frame_index": 253, "skeleton": [{"pose": [0.000, 0.000, 0.000, 0.000, 0.000, 0.000, 0.000, 0.000, 0.000, 0.000, 0.110, 0.008, 0.176, 0.163, 0.309, 0.280, 0.000, 0.000, 0.000, 0.000, 0.000, 0.000, 0.000, 0.000, 0.000, 0.000, 0.000, 0.000, 0.000, 0.000, 0.000, 0.000, 0.000, 0.000, 0.000, 0.000], "score": [0.000, 0.000, 0.000, 0.000, 0.000, 0.067, 0.399, 0.562, 0.000, 0.000, 0.000, 0.000, 0.000, 0.000, 0.000, 0.000, 0.000, 0.000]}]}, {"frame_index": 254, "skeleton": [{"pose": [0.000, 0.000, 0.000, 0.000, 0.000, 0.000, 0.000, 0.000, 0.000, 0.000, 0.106, 0.008, 0.182, 0.163, 0.313, 0.277, 0.000, 0.000, 0.000, 0.000, 0.000, 0.000, 0.000, 0.000, 0.000, 0.000, 0.000, 0.000, 0.000, 0.000, 0.000, 0.000, 0.000, 0.000, 0.000, 0.000], "score": [0.000, 0.000, 0.000, 0.000, 0.000, 0.078, 0.420, 0.580, 0.000, 0.000, 0.000, 0.000, 0.000, 0.000, 0.000, 0.000, 0.000, 0.000]}]}, {"frame_index": 255, "skeleton": [{"pose": [0.000, 0.000, 0.000, 0.000, 0.000, 0.000, 0.000, 0.000, 0.000, 0.000, 0.102, 0.008, 0.174, 0.163, 0.309, 0.272, 0.000, 0.000, 0.000, 0.000, 0.000, 0.000, 0.000, 0.000, 0.000, 0.000, 0.000, 0.000, 0.000, 0.000, 0.000, 0.000, 0.000, 0.000, 0.000, 0.000], "score": [0.000, 0.000, 0.000, 0.000, 0.000, 0.074, 0.429, 0.598, 0.000, 0.000, 0.000, 0.000, 0.000, 0.000, 0.000, 0.000, 0.000, 0.000]}]}, {"frame_index": 256, "skeleton": [{"pose": [0.000, 0.000, 0.000, 0.000, 0.000, 0.000, 0.000, 0.000, 0.000, 0.000, 0.100, 0.008, 0.168, 0.179, 0.297, 0.272, 0.000, 0.000, 0.000, 0.000, 0.000, 0.000, 0.000, 0.000, 0.000, 0.000, 0.000, 0.000, 0.000, 0.000, 0.000, 0.000, 0.000, 0.000, 0.000, 0.000], "score": [0.000, 0.000, 0.000, 0.000, 0.000, 0.080, 0.429, 0.619, 0.000, 0.000, 0.000, 0.000, 0.000, 0.000, 0.000, 0.000, 0.000, 0.000]}]}, {"frame_index": 257, "skeleton": [{"pose": [0.000, 0.000, 0.000, 0.000, 0.000, 0.000, 0.000, 0.000, 0.000, 0.000, 0.096, 0.008, 0.162, 0.187, 0.286, 0.274, 0.000, 0.000, 0.000, 0.000, 0.000, 0.000, 0.000, 0.000, 0.000, 0.000, 0.000, 0.000, 0.000, 0.000, 0.000, 0.000, 0.000, 0.000, 0.000, 0.000], "score": [0.000, 0.000, 0.000, 0.000, 0.000, 0.079, 0.413, 0.596, 0.000, 0.000, 0.000, 0.000, 0.000, 0.000, 0.000, 0.000, 0.000, 0.000]}]}, {"frame_index": 258, "skeleton": [{"pose": [0.000, 0.000, 0.000, 0.000, 0.000, 0.000, 0.000, 0.000, 0.000, 0.000, 0.086, 0.008, 0.166, 0.198, 0.278, 0.291, 0.000, 0.000, 0.000, 0.000, 0.000, 0.000, 0.000, 0.000, 0.000, 0.000, 0.000, 0.000, 0.000, 0.000, 0.000, 0.000, 0.000, 0.000, 0.000, 0.000], "score": [0.000, 0.000, 0.000, 0.000, 0.000, 0.055, 0.329, 0.526, 0.000, 0.000, 0.000, 0.000, 0.000, 0.000, 0.000, 0.000, 0.000, 0.000]}]}, {"frame_index": 259, "skeleton": [{"pose": [0.000, 0.000, 0.000, 0.000, 0.000, 0.000, 0.000, 0.000, 0.000, 0.000, 0.082, 0.008, 0.156, 0.196, 0.270, 0.296, 0.000, 0.000, 0.000, 0.000, 0.000, 0.000, 0.000, 0.000, 0.000, 0.000, 0.000, 0.000, 0.000, 0.000, 0.000, 0.000, 0.000, 0.000, 0.000, 0.000], "score": [0.000, 0.000, 0.000, 0.000, 0.000, 0.054, 0.292, 0.590, 0.000, 0.000, 0.000, 0.000, 0.000, 0.000, 0.000, 0.000, 0.000, 0.000]}]}, {"frame_index": 260, "skeleton": []}, {"frame_index": 261, "skeleton": []}, {"frame_index": 262, "skeleton": []}, {"frame_index": 263, "skeleton": []}, {"frame_index": 264, "skeleton": []}, {"frame_index": 265, "skeleton": []}, {"frame_index": 266, "skeleton": []}, {"frame_index": 267, "skeleton": []}, {"frame_index": 268, "skeleton": []}, {"frame_index": 269, "skeleton": []}, {"frame_index": 270, "skeleton": []}, {"frame_index": 271, "skeleton": []}, {"frame_index": 272, "skeleton": []}, {"frame_index": 273, "skeleton": []}, {"frame_index": 274, "skeleton": []}, {"frame_index": 275, "skeleton": []}, {"frame_index": 276, "skeleton": []}, {"frame_index": 277, "skeleton": [{"pose": [0.000, 0.000, 0.172, 0.234, 0.143, 0.258, 0.000, 0.000, 0.000, 0.000, 0.209, 0.209, 0.299, 0.299, 0.366, 0.272, 0.264, 0.492, 0.000, 0.000, 0.000, 0.000, 0.309, 0.443, 0.000, 0.000, 0.000, 0.000, 0.000, 0.000, 0.000, 0.000, 0.000, 0.000, 0.186, 0.160], "score": [0.000, 0.104, 0.055, 0.000, 0.000, 0.330, 0.598, 0.754, 0.057, 0.000, 0.000, 0.103, 0.000, 0.000, 0.000, 0.000, 0.000, 0.100]}]}, {"frame_index": 278, "skeleton": [{"pose": [0.000, 0.000, 0.170, 0.220, 0.000, 0.000, 0.000, 0.000, 0.000, 0.000, 0.213, 0.198, 0.301, 0.272, 0.372, 0.266, 0.000, 0.000, 0.000, 0.000, 0.000, 0.000, 0.000, 0.000, 0.000, 0.000, 0.000, 0.000, 0.000, 0.000, 0.000, 0.000, 0.000, 0.000, 0.186, 0.147], "score": [0.000, 0.067, 0.000, 0.000, 0.000, 0.270, 0.483, 0.610, 0.000, 0.000, 0.000, 0.000, 0.000, 0.000, 0.000, 0.000, 0.000, 0.106]}]}, {"frame_index": 279, "skeleton": []}, {"frame_index": 280, "skeleton": []}, {"frame_index": 281, "skeleton": [{"pose": [0.000, 0.000, 0.000, 0.000, 0.000, 0.000, 0.000, 0.000, 0.000, 0.000, 0.110, 0.008, 0.196, 0.141, 0.315, 0.220, 0.000, 0.000, 0.000, 0.000, 0.000, 0.000, 0.000, 0.000, 0.000, 0.000, 0.000, 0.000, 0.000, 0.000, 0.000, 0.000, 0.000, 0.000, 0.000, 0.000], "score": [0.000, 0.000, 0.000, 0.000, 0.000, 0.083, 0.333, 0.525, 0.000, 0.000, 0.000, 0.000, 0.000, 0.000, 0.000, 0.000, 0.000, 0.000]}]}, {"frame_index": 282, "skeleton": [{"pose": [0.000, 0.000, 0.000, 0.000, 0.104, 0.008, 0.211, 0.155, 0.317, 0.215, 0.000, 0.000, 0.000, 0.000, 0.000, 0.000, 0.000, 0.000, 0.000, 0.000, 0.000, 0.000, 0.000, 0.000, 0.000, 0.000, 0.000, 0.000, 0.000, 0.000, 0.000, 0.000, 0.000, 0.000, 0.000, 0.000], "score": [0.000, 0.000, 0.072, 0.287, 0.478, 0.000, 0.000, 0.000, 0.000, 0.000, 0.000, 0.000, 0.000, 0.000, 0.000, 0.000, 0.000, 0.000]}]}, {"frame_index": 283, "skeleton": []}, {"frame_index": 284, "skeleton": []}, {"frame_index": 285, "skeleton": [{"pose": [0.000, 0.000, 0.000, 0.000, 0.127, 0.008, 0.209, 0.144, 0.331, 0.225, 0.000, 0.000, 0.000, 0.000, 0.000, 0.000, 0.000, 0.000, 0.000, 0.000, 0.000, 0.000, 0.000, 0.000, 0.000, 0.000, 0.000, 0.000, 0.000, 0.000, 0.000, 0.000, 0.000, 0.000, 0.000, 0.000], "score": [0.000, 0.000, 0.065, 0.269, 0.399, 0.000, 0.000, 0.000, 0.000, 0.000, 0.000, 0.000, 0.000, 0.000, 0.000, 0.000, 0.000, 0.000]}]}, {"frame_index": 286, "skeleton": []}, {"frame_index": 287, "skeleton": [{"pose": [0.000, 0.000, 0.027, 0.008, 0.131, 0.008, 0.229, 0.163, 0.336, 0.245, 0.000, 0.000, 0.000, 0.000, 0.000, 0.000, 0.268, 0.394, 0.399, 0.429, 0.442, 0.451, 0.000, 0.000, 0.000, 0.000, 0.000, 0.000, 0.000, 0.000, 0.000, 0.000, 0.000, 0.000, 0.000, 0.000], "score": [0.000, 0.060, 0.078, 0.327, 0.463, 0.000, 0.000, 0.000, 0.107, 0.285, 0.067, 0.000, 0.000, 0.000, 0.000, 0.000, 0.000, 0.000]}]}, {"frame_index": 288, "skeleton": [{"pose": [0.000, 0.000, 0.000, 0.000, 0.129, 0.008, 0.219, 0.152, 0.338, 0.245, 0.000, 0.000, 0.000, 0.000, 0.000, 0.000, 0.000, 0.000, 0.000, 0.000, 0.000, 0.000, 0.000, 0.000, 0.000, 0.000, 0.000, 0.000, 0.000, 0.000, 0.000, 0.000, 0.000, 0.000, 0.000, 0.000], "score": [0.000, 0.000, 0.066, 0.239, 0.321, 0.000, 0.000, 0.000, 0.000, 0.000, 0.000, 0.000, 0.000, 0.000, 0.000, 0.000, 0.000, 0.000]}]}, {"frame_index": 289, "skeleton": [{"pose": [0.000, 0.000, 0.000, 0.000, 0.000, 0.000, 0.000, 0.000, 0.000, 0.000, 0.153, 0.008, 0.237, 0.147, 0.338, 0.247, 0.000, 0.000, 0.000, 0.000, 0.000, 0.000, 0.000, 0.000, 0.000, 0.000, 0.000, 0.000, 0.000, 0.000, 0.000, 0.000, 0.000, 0.000, 0.000, 0.000], "score": [0.000, 0.000, 0.000, 0.000, 0.000, 0.054, 0.242, 0.317, 0.000, 0.000, 0.000, 0.000, 0.000, 0.000, 0.000, 0.000, 0.000, 0.000]}]}, {"frame_index": 290, "skeleton": [{"pose": [0.000, 0.000, 0.029, 0.008, 0.143, 0.008, 0.237, 0.163, 0.350, 0.250, 0.000, 0.000, 0.000, 0.000, 0.000, 0.000, 0.223, 0.359, 0.405, 0.435, 0.000, 0.000, 0.000, 0.000, 0.000, 0.000, 0.000, 0.000, 0.000, 0.000, 0.000, 0.000, 0.000, 0.000, 0.000, 0.000], "score": [0.000, 0.052, 0.094, 0.319, 0.546, 0.000, 0.000, 0.000, 0.068, 0.224, 0.000, 0.000, 0.000, 0.000, 0.000, 0.000, 0.000, 0.000]}]}, {"frame_index": 291, "skeleton": [{"pose": [0.000, 0.000, 0.000, 0.000, 0.262, 0.179, 0.417, 0.310, 0.352, 0.242, 0.000, 0.000, 0.000, 0.000, 0.000, 0.000, 0.000, 0.000, 0.000, 0.000, 0.000, 0.000, 0.000, 0.000, 0.000, 0.000, 0.000, 0.000, 0.000, 0.000, 0.000, 0.000, 0.000, 0.000, 0.000, 0.000], "score": [0.000, 0.000, 0.103, 0.641, 0.058, 0.000, 0.000, 0.000, 0.000, 0.000, 0.000, 0.000, 0.000, 0.000, 0.000, 0.000, 0.000, 0.000]}]}, {"frame_index": 292, "skeleton": [{"pose": [0.000, 0.000, 0.000, 0.000, 0.151, 0.008, 0.237, 0.166, 0.360, 0.253, 0.000, 0.000, 0.000, 0.000, 0.000, 0.000, 0.000, 0.000, 0.000, 0.000, 0.000, 0.000, 0.000, 0.000, 0.000, 0.000, 0.000, 0.000, 0.000, 0.000, 0.000, 0.000, 0.000, 0.000, 0.000, 0.000], "score": [0.000, 0.000, 0.083, 0.298, 0.411, 0.000, 0.000, 0.000, 0.000, 0.000, 0.000, 0.000, 0.000, 0.000, 0.000, 0.000, 0.000, 0.000]}]}, {"frame_index": 293, "skeleton": [{"pose": [0.000, 0.000, 0.000, 0.000, 0.153, 0.008, 0.239, 0.171, 0.366, 0.264, 0.000, 0.000, 0.000, 0.000, 0.000, 0.000, 0.000, 0.000, 0.000, 0.000, 0.000, 0.000, 0.000, 0.000, 0.000, 0.000, 0.000, 0.000, 0.000, 0.000, 0.000, 0.000, 0.000, 0.000, 0.000, 0.000], "score": [0.000, 0.000, 0.060, 0.293, 0.522, 0.000, 0.000, 0.000, 0.000, 0.000, 0.000, 0.000, 0.000, 0.000, 0.000, 0.000, 0.000, 0.000]}]}, {"frame_index": 294, "skeleton": [{"pose": [0.000, 0.000, 0.000, 0.000, 0.158, 0.008, 0.250, 0.182, 0.370, 0.266, 0.000, 0.000, 0.000, 0.000, 0.000, 0.000, 0.000, 0.000, 0.000, 0.000, 0.000, 0.000, 0.000, 0.000, 0.000, 0.000, 0.000, 0.000, 0.000, 0.000, 0.000, 0.000, 0.000, 0.000, 0.000, 0.000], "score": [0.000, 0.000, 0.054, 0.258, 0.468, 0.000, 0.000, 0.000, 0.000, 0.000, 0.000, 0.000, 0.000, 0.000, 0.000, 0.000, 0.000, 0.000]}]}, {"frame_index": 295, "skeleton": [{"pose": [0.000, 0.000, 0.000, 0.000, 0.160, 0.008, 0.252, 0.171, 0.370, 0.269, 0.000, 0.000, 0.000, 0.000, 0.000, 0.000, 0.000, 0.000, 0.000, 0.000, 0.000, 0.000, 0.000, 0.000, 0.000, 0.000, 0.000, 0.000, 0.000, 0.000, 0.000, 0.000, 0.000, 0.000, 0.000, 0.000], "score": [0.000, 0.000, 0.064, 0.308, 0.591, 0.000, 0.000, 0.000, 0.000, 0.000, 0.000, 0.000, 0.000, 0.000, 0.000, 0.000, 0.000, 0.000]}]}, {"frame_index": 296, "skeleton": [{"pose": [0.000, 0.000, 0.000, 0.000, 0.156, 0.008, 0.256, 0.168, 0.376, 0.269, 0.000, 0.000, 0.000, 0.000, 0.000, 0.000, 0.000, 0.000, 0.000, 0.000, 0.000, 0.000, 0.000, 0.000, 0.000, 0.000, 0.000, 0.000, 0.000, 0.000, 0.000, 0.000, 0.000, 0.000, 0.000, 0.000], "score": [0.000, 0.000, 0.061, 0.294, 0.610, 0.000, 0.000, 0.000, 0.000, 0.000, 0.000, 0.000, 0.000, 0.000, 0.000, 0.000, 0.000, 0.000]}]}, {"frame_index": 297, "skeleton": [{"pose": [0.000, 0.000, 0.000, 0.000, 0.160, 0.008, 0.264, 0.168, 0.383, 0.269, 0.000, 0.000, 0.000, 0.000, 0.000, 0.000, 0.000, 0.000, 0.000, 0.000, 0.000, 0.000, 0.000, 0.000, 0.000, 0.000, 0.000, 0.000, 0.000, 0.000, 0.000, 0.000, 0.000, 0.000, 0.000, 0.000], "score": [0.000, 0.000, 0.052, 0.261, 0.656, 0.000, 0.000, 0.000, 0.000, 0.000, 0.000, 0.000, 0.000, 0.000, 0.000, 0.000, 0.000, 0.000]}]}, {"frame_index": 298, "skeleton": []}, {"frame_index": 299, "skeleton": []}], "label": "unboxing", "label_index": 371}