{"data": [{"frame_index": 1, "skeleton": []}, {"frame_index": 2, "skeleton": []}, {"frame_index": 3, "skeleton": []}, {"frame_index": 4, "skeleton": []}, {"frame_index": 5, "skeleton": []}, {"frame_index": 6, "skeleton": []}, {"frame_index": 7, "skeleton": []}, {"frame_index": 8, "skeleton": []}, {"frame_index": 9, "skeleton": []}, {"frame_index": 10, "skeleton": []}, {"frame_index": 11, "skeleton": []}, {"frame_index": 12, "skeleton": []}, {"frame_index": 13, "skeleton": []}, {"frame_index": 14, "skeleton": []}, {"frame_index": 15, "skeleton": []}, {"frame_index": 16, "skeleton": []}, {"frame_index": 17, "skeleton": []}, {"frame_index": 18, "skeleton": []}, {"frame_index": 19, "skeleton": []}, {"frame_index": 20, "skeleton": []}, {"frame_index": 21, "skeleton": []}, {"frame_index": 22, "skeleton": []}, {"frame_index": 23, "skeleton": []}, {"frame_index": 24, "skeleton": [{"pose": [0.278, 0.660, 0.000, 0.000, 0.000, 0.000, 0.000, 0.000, 0.000, 0.000, 0.000, 0.000, 0.000, 0.000, 0.000, 0.000, 0.000, 0.000, 0.000, 0.000, 0.000, 0.000, 0.000, 0.000, 0.000, 0.000, 0.000, 0.000, 0.258, 0.628, 0.303, 0.617, 0.000, 0.000, 0.350, 0.601], "score": [0.278, 0.000, 0.000, 0.000, 0.000, 0.000, 0.000, 0.000, 0.000, 0.000, 0.000, 0.000, 0.000, 0.000, 0.345, 0.352, 0.000, 0.132]}]}, {"frame_index": 25, "skeleton": [{"pose": [0.282, 0.660, 0.000, 0.000, 0.000, 0.000, 0.000, 0.000, 0.000, 0.000, 0.000, 0.000, 0.000, 0.000, 0.000, 0.000, 0.000, 0.000, 0.000, 0.000, 0.000, 0.000, 0.000, 0.000, 0.000, 0.000, 0.000, 0.000, 0.258, 0.628, 0.305, 0.617, 0.000, 0.000, 0.350, 0.603], "score": [0.283, 0.000, 0.000, 0.000, 0.000, 0.000, 0.000, 0.000, 0.000, 0.000, 0.000, 0.000, 0.000, 0.000, 0.363, 0.365, 0.000, 0.132]}]}, {"frame_index": 26, "skeleton": [{"pose": [0.282, 0.660, 0.000, 0.000, 0.000, 0.000, 0.000, 0.000, 0.000, 0.000, 0.000, 0.000, 0.000, 0.000, 0.000, 0.000, 0.000, 0.000, 0.000, 0.000, 0.000, 0.000, 0.000, 0.000, 0.000, 0.000, 0.000, 0.000, 0.260, 0.630, 0.305, 0.617, 0.000, 0.000, 0.350, 0.601], "score": [0.275, 0.000, 0.000, 0.000, 0.000, 0.000, 0.000, 0.000, 0.000, 0.000, 0.000, 0.000, 0.000, 0.000, 0.353, 0.358, 0.000, 0.161]}]}, {"frame_index": 27, "skeleton": []}, {"frame_index": 28, "skeleton": []}, {"frame_index": 29, "skeleton": []}, {"frame_index": 30, "skeleton": []}, {"frame_index": 31, "skeleton": []}, {"frame_index": 32, "skeleton": []}, {"frame_index": 33, "skeleton": []}, {"frame_index": 34, "skeleton": []}, {"frame_index": 35, "skeleton": []}, {"frame_index": 36, "skeleton": []}, {"frame_index": 37, "skeleton": []}, {"frame_index": 38, "skeleton": []}, {"frame_index": 39, "skeleton": []}, {"frame_index": 40, "skeleton": []}, {"frame_index": 41, "skeleton": []}, {"frame_index": 42, "skeleton": []}, {"frame_index": 43, "skeleton": []}, {"frame_index": 44, "skeleton": []}, {"frame_index": 45, "skeleton": []}, {"frame_index": 46, "skeleton": []}, {"frame_index": 47, "skeleton": []}, {"frame_index": 48, "skeleton": []}, {"frame_index": 49, "skeleton": []}, {"frame_index": 50, "skeleton": []}, {"frame_index": 51, "skeleton": []}, {"frame_index": 52, "skeleton": []}, {"frame_index": 53, "skeleton": []}, {"frame_index": 54, "skeleton": []}, {"frame_index": 55, "skeleton": []}, {"frame_index": 56, "skeleton": []}, {"frame_index": 57, "skeleton": []}, {"frame_index": 58, "skeleton": []}, {"frame_index": 59, "skeleton": []}, {"frame_index": 60, "skeleton": []}, {"frame_index": 61, "skeleton": []}, {"frame_index": 62, "skeleton": []}, {"frame_index": 63, "skeleton": []}, {"frame_index": 64, "skeleton": []}, {"frame_index": 65, "skeleton": []}, {"frame_index": 66, "skeleton": []}, {"frame_index": 67, "skeleton": []}, {"frame_index": 68, "skeleton": []}, {"frame_index": 69, "skeleton": []}, {"frame_index": 70, "skeleton": []}, {"frame_index": 71, "skeleton": []}, {"frame_index": 72, "skeleton": []}, {"frame_index": 73, "skeleton": []}, {"frame_index": 74, "skeleton": []}, {"frame_index": 75, "skeleton": []}, {"frame_index": 76, "skeleton": []}, {"frame_index": 77, "skeleton": []}, {"frame_index": 78, "skeleton": []}, {"frame_index": 79, "skeleton": []}, {"frame_index": 80, "skeleton": []}, {"frame_index": 81, "skeleton": []}, {"frame_index": 82, "skeleton": []}, {"frame_index": 83, "skeleton": []}, {"frame_index": 84, "skeleton": []}, {"frame_index": 85, "skeleton": []}, {"frame_index": 86, "skeleton": []}, {"frame_index": 87, "skeleton": []}, {"frame_index": 88, "skeleton": []}, {"frame_index": 89, "skeleton": []}, {"frame_index": 90, "skeleton": []}, {"frame_index": 91, "skeleton": []}, {"frame_index": 92, "skeleton": []}, {"frame_index": 93, "skeleton": []}, {"frame_index": 94, "skeleton": []}, {"frame_index": 95, "skeleton": []}, {"frame_index": 96, "skeleton": []}, {"frame_index": 97, "skeleton": []}, {"frame_index": 98, "skeleton": []}, {"frame_index": 99, "skeleton": []}, {"frame_index": 100, "skeleton": []}, {"frame_index": 101, "skeleton": []}, {"frame_index": 102, "skeleton": []}, {"frame_index": 103, "skeleton": []}, {"frame_index": 104, "skeleton": []}, {"frame_index": 105, "skeleton": []}, {"frame_index": 106, "skeleton": []}, {"frame_index": 107, "skeleton": []}, {"frame_index": 108, "skeleton": []}, {"frame_index": 109, "skeleton": []}, {"frame_index": 110, "skeleton": []}, {"frame_index": 111, "skeleton": []}, {"frame_index": 112, "skeleton": []}, {"frame_index": 113, "skeleton": []}, {"frame_index": 114, "skeleton": []}, {"frame_index": 115, "skeleton": []}, {"frame_index": 116, "skeleton": []}, {"frame_index": 117, "skeleton": []}, {"frame_index": 118, "skeleton": [{"pose": [0.000, 0.000, 0.595, 0.356, 0.548, 0.340, 0.518, 0.486, 0.000, 0.000, 0.642, 0.361, 0.647, 0.465, 0.632, 0.467, 0.000, 0.000, 0.000, 0.000, 0.000, 0.000, 0.000, 0.000, 0.000, 0.000, 0.000, 0.000, 0.000, 0.000, 0.000, 0.000, 0.595, 0.367, 0.000, 0.000], "score": [0.000, 0.416, 0.498, 0.211, 0.000, 0.364, 0.180, 0.133, 0.000, 0.000, 0.000, 0.000, 0.000, 0.000, 0.000, 0.000, 0.052, 0.000]}]}, {"frame_index": 119, "skeleton": [{"pose": [0.000, 0.000, 0.595, 0.356, 0.548, 0.337, 0.518, 0.486, 0.000, 0.000, 0.644, 0.361, 0.646, 0.465, 0.622, 0.448, 0.544, 0.533, 0.000, 0.000, 0.000, 0.000, 0.622, 0.527, 0.000, 0.000, 0.000, 0.000, 0.000, 0.000, 0.000, 0.000, 0.595, 0.367, 0.000, 0.000], "score": [0.000, 0.531, 0.538, 0.272, 0.000, 0.463, 0.278, 0.147, 0.056, 0.000, 0.000, 0.054, 0.000, 0.000, 0.000, 0.000, 0.063, 0.000]}]}, {"frame_index": 120, "skeleton": [{"pose": [0.000, 0.000, 0.597, 0.361, 0.550, 0.337, 0.518, 0.478, 0.000, 0.000, 0.644, 0.378, 0.647, 0.467, 0.626, 0.462, 0.000, 0.000, 0.000, 0.000, 0.000, 0.000, 0.000, 0.000, 0.000, 0.000, 0.000, 0.000, 0.000, 0.000, 0.000, 0.000, 0.595, 0.375, 0.000, 0.000], "score": [0.000, 0.318, 0.486, 0.230, 0.000, 0.239, 0.138, 0.054, 0.000, 0.000, 0.000, 0.000, 0.000, 0.000, 0.000, 0.000, 0.083, 0.000]}]}, {"frame_index": 121, "skeleton": []}, {"frame_index": 122, "skeleton": []}, {"frame_index": 123, "skeleton": []}, {"frame_index": 124, "skeleton": []}, {"frame_index": 125, "skeleton": []}, {"frame_index": 126, "skeleton": []}, {"frame_index": 127, "skeleton": []}, {"frame_index": 128, "skeleton": [{"pose": [0.597, 0.451, 0.604, 0.367, 0.557, 0.340, 0.522, 0.473, 0.000, 0.000, 0.649, 0.378, 0.659, 0.467, 0.000, 0.000, 0.000, 0.000, 0.000, 0.000, 0.000, 0.000, 0.000, 0.000, 0.000, 0.000, 0.000, 0.000, 0.595, 0.427, 0.000, 0.000, 0.597, 0.383, 0.000, 0.000], "score": [0.130, 0.264, 0.466, 0.223, 0.000, 0.180, 0.080, 0.000, 0.000, 0.000, 0.000, 0.000, 0.000, 0.000, 0.143, 0.000, 0.107, 0.000]}]}, {"frame_index": 129, "skeleton": [{"pose": [0.000, 0.000, 0.599, 0.367, 0.554, 0.337, 0.520, 0.476, 0.000, 0.000, 0.645, 0.378, 0.000, 0.000, 0.000, 0.000, 0.000, 0.000, 0.000, 0.000, 0.000, 0.000, 0.000, 0.000, 0.000, 0.000, 0.000, 0.000, 0.000, 0.000, 0.000, 0.000, 0.597, 0.383, 0.000, 0.000], "score": [0.000, 0.210, 0.440, 0.228, 0.000, 0.123, 0.000, 0.000, 0.000, 0.000, 0.000, 0.000, 0.000, 0.000, 0.000, 0.000, 0.095, 0.000]}]}, {"frame_index": 130, "skeleton": [{"pose": [0.000, 0.000, 0.600, 0.359, 0.552, 0.337, 0.518, 0.484, 0.000, 0.000, 0.647, 0.364, 0.659, 0.470, 0.000, 0.000, 0.000, 0.000, 0.000, 0.000, 0.000, 0.000, 0.000, 0.000, 0.000, 0.000, 0.000, 0.000, 0.000, 0.000, 0.000, 0.000, 0.000, 0.000, 0.000, 0.000], "score": [0.000, 0.253, 0.435, 0.204, 0.000, 0.175, 0.051, 0.000, 0.000, 0.000, 0.000, 0.000, 0.000, 0.000, 0.000, 0.000, 0.000, 0.000]}]}, {"frame_index": 131, "skeleton": []}, {"frame_index": 132, "skeleton": [{"pose": [0.000, 0.000, 0.595, 0.361, 0.552, 0.340, 0.520, 0.478, 0.000, 0.000, 0.642, 0.367, 0.000, 0.000, 0.000, 0.000, 0.000, 0.000, 0.000, 0.000, 0.000, 0.000, 0.000, 0.000, 0.000, 0.000, 0.000, 0.000, 0.000, 0.000, 0.000, 0.000, 0.000, 0.000, 0.000, 0.000], "score": [0.000, 0.169, 0.405, 0.175, 0.000, 0.091, 0.000, 0.000, 0.000, 0.000, 0.000, 0.000, 0.000, 0.000, 0.000, 0.000, 0.000, 0.000]}]}, {"frame_index": 133, "skeleton": [{"pose": [0.000, 0.000, 0.597, 0.359, 0.550, 0.340, 0.516, 0.481, 0.000, 0.000, 0.645, 0.361, 0.657, 0.470, 0.640, 0.467, 0.000, 0.000, 0.000, 0.000, 0.000, 0.000, 0.000, 0.000, 0.000, 0.000, 0.000, 0.000, 0.000, 0.000, 0.000, 0.000, 0.595, 0.383, 0.000, 0.000], "score": [0.000, 0.307, 0.514, 0.274, 0.000, 0.214, 0.054, 0.062, 0.000, 0.000, 0.000, 0.000, 0.000, 0.000, 0.000, 0.000, 0.068, 0.000]}]}, {"frame_index": 134, "skeleton": [{"pose": [0.000, 0.000, 0.597, 0.361, 0.550, 0.340, 0.516, 0.476, 0.000, 0.000, 0.644, 0.370, 0.000, 0.000, 0.000, 0.000, 0.000, 0.000, 0.000, 0.000, 0.000, 0.000, 0.000, 0.000, 0.000, 0.000, 0.000, 0.000, 0.000, 0.000, 0.000, 0.000, 0.595, 0.386, 0.000, 0.000], "score": [0.000, 0.209, 0.425, 0.194, 0.000, 0.114, 0.000, 0.000, 0.000, 0.000, 0.000, 0.000, 0.000, 0.000, 0.000, 0.000, 0.115, 0.000]}]}, {"frame_index": 135, "skeleton": [{"pose": [0.000, 0.000, 0.597, 0.356, 0.550, 0.337, 0.516, 0.478, 0.000, 0.000, 0.644, 0.361, 0.000, 0.000, 0.000, 0.000, 0.000, 0.000, 0.000, 0.000, 0.000, 0.000, 0.000, 0.000, 0.000, 0.000, 0.000, 0.000, 0.000, 0.000, 0.000, 0.000, 0.000, 0.000, 0.000, 0.000], "score": [0.000, 0.243, 0.454, 0.228, 0.000, 0.163, 0.000, 0.000, 0.000, 0.000, 0.000, 0.000, 0.000, 0.000, 0.000, 0.000, 0.000, 0.000]}]}, {"frame_index": 136, "skeleton": []}, {"frame_index": 137, "skeleton": []}, {"frame_index": 138, "skeleton": [{"pose": [0.000, 0.000, 0.597, 0.356, 0.552, 0.337, 0.516, 0.470, 0.000, 0.000, 0.645, 0.361, 0.655, 0.465, 0.000, 0.000, 0.000, 0.000, 0.000, 0.000, 0.000, 0.000, 0.000, 0.000, 0.000, 0.000, 0.000, 0.000, 0.000, 0.000, 0.000, 0.000, 0.595, 0.375, 0.000, 0.000], "score": [0.000, 0.307, 0.470, 0.274, 0.000, 0.226, 0.078, 0.000, 0.000, 0.000, 0.000, 0.000, 0.000, 0.000, 0.000, 0.000, 0.061, 0.000]}]}, {"frame_index": 139, "skeleton": [{"pose": [0.000, 0.000, 0.597, 0.359, 0.552, 0.337, 0.518, 0.478, 0.000, 0.000, 0.642, 0.364, 0.000, 0.000, 0.000, 0.000, 0.000, 0.000, 0.000, 0.000, 0.000, 0.000, 0.000, 0.000, 0.000, 0.000, 0.000, 0.000, 0.000, 0.000, 0.000, 0.000, 0.000, 0.000, 0.000, 0.000], "score": [0.000, 0.205, 0.381, 0.145, 0.000, 0.115, 0.000, 0.000, 0.000, 0.000, 0.000, 0.000, 0.000, 0.000, 0.000, 0.000, 0.000, 0.000]}]}, {"frame_index": 140, "skeleton": []}, {"frame_index": 141, "skeleton": [{"pose": [0.000, 0.000, 0.597, 0.356, 0.552, 0.337, 0.520, 0.484, 0.000, 0.000, 0.645, 0.359, 0.000, 0.000, 0.000, 0.000, 0.000, 0.000, 0.000, 0.000, 0.000, 0.000, 0.000, 0.000, 0.000, 0.000, 0.000, 0.000, 0.000, 0.000, 0.000, 0.000, 0.000, 0.000, 0.000, 0.000], "score": [0.000, 0.261, 0.403, 0.178, 0.000, 0.199, 0.000, 0.000, 0.000, 0.000, 0.000, 0.000, 0.000, 0.000, 0.000, 0.000, 0.000, 0.000]}]}, {"frame_index": 142, "skeleton": []}, {"frame_index": 143, "skeleton": []}, {"frame_index": 144, "skeleton": []}, {"frame_index": 145, "skeleton": []}, {"frame_index": 146, "skeleton": []}, {"frame_index": 147, "skeleton": []}, {"frame_index": 148, "skeleton": []}, {"frame_index": 149, "skeleton": []}, {"frame_index": 150, "skeleton": []}, {"frame_index": 151, "skeleton": []}, {"frame_index": 152, "skeleton": []}, {"frame_index": 153, "skeleton": []}, {"frame_index": 154, "skeleton": []}, {"frame_index": 155, "skeleton": []}, {"frame_index": 156, "skeleton": []}, {"frame_index": 157, "skeleton": [{"pose": [0.000, 0.000, 0.610, 0.359, 0.563, 0.337, 0.526, 0.467, 0.000, 0.000, 0.649, 0.370, 0.000, 0.000, 0.000, 0.000, 0.000, 0.000, 0.000, 0.000, 0.000, 0.000, 0.000, 0.000, 0.000, 0.000, 0.000, 0.000, 0.000, 0.000, 0.000, 0.000, 0.000, 0.000, 0.000, 0.000], "score": [0.000, 0.157, 0.468, 0.172, 0.000, 0.079, 0.000, 0.000, 0.000, 0.000, 0.000, 0.000, 0.000, 0.000, 0.000, 0.000, 0.000, 0.000]}]}, {"frame_index": 158, "skeleton": [{"pose": [0.000, 0.000, 0.608, 0.359, 0.563, 0.337, 0.528, 0.467, 0.000, 0.000, 0.649, 0.370, 0.000, 0.000, 0.000, 0.000, 0.000, 0.000, 0.000, 0.000, 0.000, 0.000, 0.000, 0.000, 0.000, 0.000, 0.000, 0.000, 0.000, 0.000, 0.000, 0.000, 0.000, 0.000, 0.000, 0.000], "score": [0.000, 0.187, 0.433, 0.176, 0.000, 0.098, 0.000, 0.000, 0.000, 0.000, 0.000, 0.000, 0.000, 0.000, 0.000, 0.000, 0.000, 0.000]}]}, {"frame_index": 159, "skeleton": []}, {"frame_index": 160, "skeleton": []}, {"frame_index": 161, "skeleton": [{"pose": [0.000, 0.000, 0.610, 0.359, 0.563, 0.334, 0.530, 0.467, 0.000, 0.000, 0.647, 0.359, 0.000, 0.000, 0.000, 0.000, 0.000, 0.000, 0.000, 0.000, 0.000, 0.000, 0.000, 0.000, 0.000, 0.000, 0.000, 0.000, 0.000, 0.000, 0.000, 0.000, 0.630, 0.397, 0.000, 0.000], "score": [0.000, 0.300, 0.536, 0.303, 0.000, 0.175, 0.000, 0.000, 0.000, 0.000, 0.000, 0.000, 0.000, 0.000, 0.000, 0.000, 0.093, 0.000]}]}, {"frame_index": 162, "skeleton": []}, {"frame_index": 163, "skeleton": [{"pose": [0.000, 0.000, 0.610, 0.361, 0.565, 0.334, 0.528, 0.459, 0.000, 0.000, 0.649, 0.367, 0.000, 0.000, 0.000, 0.000, 0.000, 0.000, 0.000, 0.000, 0.000, 0.000, 0.000, 0.000, 0.000, 0.000, 0.000, 0.000, 0.000, 0.000, 0.000, 0.000, 0.608, 0.361, 0.000, 0.000], "score": [0.000, 0.270, 0.519, 0.282, 0.000, 0.136, 0.000, 0.000, 0.000, 0.000, 0.000, 0.000, 0.000, 0.000, 0.000, 0.000, 0.068, 0.000]}]}, {"frame_index": 164, "skeleton": [{"pose": [0.000, 0.000, 0.612, 0.359, 0.565, 0.334, 0.530, 0.465, 0.595, 0.443, 0.653, 0.378, 0.000, 0.000, 0.000, 0.000, 0.000, 0.000, 0.000, 0.000, 0.000, 0.000, 0.000, 0.000, 0.000, 0.000, 0.000, 0.000, 0.000, 0.000, 0.000, 0.000, 0.610, 0.356, 0.000, 0.000], "score": [0.000, 0.268, 0.569, 0.376, 0.062, 0.131, 0.000, 0.000, 0.000, 0.000, 0.000, 0.000, 0.000, 0.000, 0.000, 0.000, 0.061, 0.000]}]}, {"frame_index": 165, "skeleton": [{"pose": [0.000, 0.000, 0.612, 0.356, 0.565, 0.334, 0.528, 0.467, 0.000, 0.000, 0.657, 0.370, 0.659, 0.457, 0.649, 0.465, 0.000, 0.000, 0.000, 0.000, 0.000, 0.000, 0.000, 0.000, 0.000, 0.000, 0.000, 0.000, 0.000, 0.000, 0.000, 0.000, 0.606, 0.359, 0.000, 0.000], "score": [0.000, 0.380, 0.610, 0.388, 0.000, 0.225, 0.056, 0.146, 0.000, 0.000, 0.000, 0.000, 0.000, 0.000, 0.000, 0.000, 0.078, 0.000]}]}, {"frame_index": 166, "skeleton": [{"pose": [0.000, 0.000, 0.612, 0.356, 0.565, 0.334, 0.526, 0.470, 0.000, 0.000, 0.647, 0.361, 0.000, 0.000, 0.000, 0.000, 0.000, 0.000, 0.000, 0.000, 0.000, 0.000, 0.000, 0.000, 0.000, 0.000, 0.000, 0.000, 0.000, 0.000, 0.000, 0.000, 0.608, 0.364, 0.000, 0.000], "score": [0.000, 0.201, 0.493, 0.272, 0.000, 0.103, 0.000, 0.000, 0.000, 0.000, 0.000, 0.000, 0.000, 0.000, 0.000, 0.000, 0.062, 0.000]}]}, {"frame_index": 167, "skeleton": []}, {"frame_index": 168, "skeleton": [{"pose": [0.000, 0.000, 0.612, 0.356, 0.565, 0.334, 0.532, 0.459, 0.530, 0.514, 0.655, 0.364, 0.659, 0.448, 0.000, 0.000, 0.536, 0.473, 0.481, 0.378, 0.481, 0.527, 0.000, 0.000, 0.000, 0.000, 0.000, 0.000, 0.000, 0.000, 0.000, 0.000, 0.610, 0.359, 0.000, 0.000], "score": [0.000, 0.452, 0.589, 0.265, 0.067, 0.314, 0.129, 0.000, 0.126, 0.632, 0.209, 0.000, 0.000, 0.000, 0.000, 0.000, 0.068, 0.000]}]}, {"frame_index": 169, "skeleton": [{"pose": [0.000, 0.000, 0.612, 0.356, 0.565, 0.334, 0.534, 0.448, 0.532, 0.495, 0.655, 0.361, 0.651, 0.443, 0.000, 0.000, 0.542, 0.473, 0.483, 0.378, 0.479, 0.535, 0.000, 0.000, 0.000, 0.000, 0.000, 0.000, 0.000, 0.000, 0.000, 0.000, 0.616, 0.364, 0.000, 0.000], "score": [0.000, 0.349, 0.527, 0.202, 0.054, 0.225, 0.111, 0.000, 0.096, 0.683, 0.168, 0.000, 0.000, 0.000, 0.000, 0.000, 0.080, 0.000]}]}, {"frame_index": 170, "skeleton": []}, {"frame_index": 171, "skeleton": [{"pose": [0.000, 0.000, 0.614, 0.353, 0.571, 0.329, 0.532, 0.443, 0.000, 0.000, 0.659, 0.367, 0.000, 0.000, 0.000, 0.000, 0.548, 0.503, 0.000, 0.000, 0.000, 0.000, 0.000, 0.000, 0.000, 0.000, 0.000, 0.000, 0.000, 0.000, 0.000, 0.000, 0.000, 0.000, 0.000, 0.000], "score": [0.000, 0.323, 0.514, 0.289, 0.000, 0.212, 0.000, 0.000, 0.065, 0.000, 0.000, 0.000, 0.000, 0.000, 0.000, 0.000, 0.000, 0.000]}]}, {"frame_index": 172, "skeleton": [{"pose": [0.608, 0.427, 0.614, 0.353, 0.569, 0.329, 0.532, 0.443, 0.000, 0.000, 0.659, 0.370, 0.000, 0.000, 0.000, 0.000, 0.000, 0.000, 0.000, 0.000, 0.000, 0.000, 0.000, 0.000, 0.000, 0.000, 0.000, 0.000, 0.602, 0.405, 0.626, 0.421, 0.620, 0.348, 0.000, 0.000], "score": [0.166, 0.278, 0.500, 0.260, 0.000, 0.152, 0.000, 0.000, 0.000, 0.000, 0.000, 0.000, 0.000, 0.000, 0.196, 0.164, 0.070, 0.000]}]}, {"frame_index": 173, "skeleton": []}, {"frame_index": 174, "skeleton": [{"pose": [0.000, 0.000, 0.612, 0.345, 0.565, 0.334, 0.534, 0.451, 0.000, 0.000, 0.657, 0.356, 0.663, 0.446, 0.000, 0.000, 0.540, 0.484, 0.483, 0.378, 0.483, 0.565, 0.614, 0.505, 0.000, 0.000, 0.000, 0.000, 0.000, 0.000, 0.000, 0.000, 0.000, 0.000, 0.000, 0.000], "score": [0.000, 0.429, 0.489, 0.202, 0.000, 0.392, 0.057, 0.000, 0.138, 0.723, 0.166, 0.053, 0.000, 0.000, 0.000, 0.000, 0.000, 0.000]}]}, {"frame_index": 175, "skeleton": [{"pose": [0.000, 0.000, 0.612, 0.345, 0.565, 0.334, 0.532, 0.459, 0.000, 0.000, 0.659, 0.356, 0.661, 0.443, 0.651, 0.448, 0.546, 0.486, 0.483, 0.378, 0.481, 0.552, 0.616, 0.492, 0.000, 0.000, 0.000, 0.000, 0.000, 0.000, 0.000, 0.000, 0.612, 0.353, 0.000, 0.000], "score": [0.000, 0.474, 0.557, 0.321, 0.000, 0.413, 0.129, 0.195, 0.147, 0.689, 0.152, 0.067, 0.000, 0.000, 0.000, 0.000, 0.062, 0.000]}]}, {"frame_index": 176, "skeleton": [{"pose": [0.000, 0.000, 0.614, 0.348, 0.565, 0.331, 0.544, 0.402, 0.532, 0.476, 0.661, 0.356, 0.663, 0.443, 0.653, 0.448, 0.544, 0.467, 0.483, 0.378, 0.483, 0.524, 0.616, 0.495, 0.000, 0.000, 0.000, 0.000, 0.000, 0.000, 0.000, 0.000, 0.612, 0.351, 0.000, 0.000], "score": [0.000, 0.434, 0.485, 0.184, 0.094, 0.387, 0.150, 0.224, 0.139, 0.734, 0.181, 0.061, 0.000, 0.000, 0.000, 0.000, 0.056, 0.000]}]}, {"frame_index": 177, "skeleton": []}, {"frame_index": 178, "skeleton": [{"pose": [0.000, 0.000, 0.612, 0.359, 0.567, 0.332, 0.540, 0.399, 0.534, 0.459, 0.659, 0.367, 0.661, 0.448, 0.659, 0.448, 0.536, 0.467, 0.483, 0.378, 0.487, 0.519, 0.000, 0.000, 0.000, 0.000, 0.000, 0.000, 0.000, 0.000, 0.000, 0.000, 0.612, 0.351, 0.000, 0.000], "score": [0.000, 0.328, 0.454, 0.150, 0.051, 0.183, 0.078, 0.054, 0.105, 0.634, 0.186, 0.000, 0.000, 0.000, 0.000, 0.000, 0.079, 0.000]}]}, {"frame_index": 179, "skeleton": [{"pose": [0.000, 0.000, 0.614, 0.342, 0.565, 0.332, 0.536, 0.454, 0.000, 0.000, 0.659, 0.356, 0.661, 0.440, 0.657, 0.446, 0.546, 0.481, 0.483, 0.378, 0.483, 0.554, 0.626, 0.489, 0.000, 0.000, 0.000, 0.000, 0.000, 0.000, 0.000, 0.000, 0.612, 0.348, 0.000, 0.000], "score": [0.000, 0.527, 0.585, 0.320, 0.000, 0.464, 0.156, 0.164, 0.158, 0.722, 0.192, 0.099, 0.000, 0.000, 0.000, 0.000, 0.055, 0.000]}]}, {"frame_index": 180, "skeleton": [{"pose": [0.000, 0.000, 0.612, 0.348, 0.567, 0.329, 0.542, 0.405, 0.538, 0.473, 0.657, 0.359, 0.661, 0.446, 0.000, 0.000, 0.546, 0.462, 0.483, 0.380, 0.481, 0.557, 0.000, 0.000, 0.000, 0.000, 0.000, 0.000, 0.000, 0.000, 0.000, 0.000, 0.612, 0.342, 0.000, 0.000], "score": [0.000, 0.386, 0.492, 0.151, 0.087, 0.301, 0.065, 0.000, 0.149, 0.745, 0.206, 0.000, 0.000, 0.000, 0.000, 0.000, 0.056, 0.000]}]}, {"frame_index": 181, "skeleton": [{"pose": [0.000, 0.000, 0.610, 0.351, 0.565, 0.332, 0.534, 0.405, 0.000, 0.000, 0.659, 0.356, 0.661, 0.443, 0.647, 0.446, 0.536, 0.446, 0.483, 0.378, 0.481, 0.511, 0.000, 0.000, 0.000, 0.000, 0.000, 0.000, 0.000, 0.000, 0.000, 0.000, 0.612, 0.359, 0.000, 0.000], "score": [0.000, 0.306, 0.389, 0.135, 0.000, 0.260, 0.111, 0.083, 0.079, 0.493, 0.116, 0.000, 0.000, 0.000, 0.000, 0.000, 0.061, 0.000]}]}, {"frame_index": 182, "skeleton": [{"pose": [0.000, 0.000, 0.612, 0.359, 0.569, 0.332, 0.532, 0.443, 0.000, 0.000, 0.659, 0.375, 0.000, 0.000, 0.000, 0.000, 0.000, 0.000, 0.000, 0.000, 0.000, 0.000, 0.000, 0.000, 0.000, 0.000, 0.000, 0.000, 0.000, 0.000, 0.000, 0.000, 0.000, 0.000, 0.000, 0.000], "score": [0.000, 0.209, 0.416, 0.190, 0.000, 0.109, 0.000, 0.000, 0.000, 0.000, 0.000, 0.000, 0.000, 0.000, 0.000, 0.000, 0.000, 0.000]}]}, {"frame_index": 183, "skeleton": []}, {"frame_index": 184, "skeleton": [{"pose": [0.000, 0.000, 0.000, 0.000, 0.000, 0.000, 0.000, 0.000, 0.000, 0.000, 0.000, 0.000, 0.000, 0.000, 0.000, 0.000, 0.532, 0.459, 0.483, 0.378, 0.475, 0.495, 0.000, 0.000, 0.000, 0.000, 0.000, 0.000, 0.000, 0.000, 0.000, 0.000, 0.000, 0.000, 0.000, 0.000], "score": [0.000, 0.000, 0.000, 0.000, 0.000, 0.000, 0.000, 0.000, 0.057, 0.518, 0.104, 0.000, 0.000, 0.000, 0.000, 0.000, 0.000, 0.000]}]}, {"frame_index": 185, "skeleton": [{"pose": [0.000, 0.000, 0.000, 0.000, 0.000, 0.000, 0.000, 0.000, 0.000, 0.000, 0.000, 0.000, 0.000, 0.000, 0.000, 0.000, 0.536, 0.462, 0.483, 0.378, 0.471, 0.519, 0.000, 0.000, 0.000, 0.000, 0.000, 0.000, 0.000, 0.000, 0.000, 0.000, 0.000, 0.000, 0.000, 0.000], "score": [0.000, 0.000, 0.000, 0.000, 0.000, 0.000, 0.000, 0.000, 0.054, 0.619, 0.122, 0.000, 0.000, 0.000, 0.000, 0.000, 0.000, 0.000]}]}, {"frame_index": 186, "skeleton": [{"pose": [0.000, 0.000, 0.000, 0.000, 0.000, 0.000, 0.000, 0.000, 0.000, 0.000, 0.000, 0.000, 0.000, 0.000, 0.000, 0.000, 0.540, 0.408, 0.483, 0.378, 0.479, 0.519, 0.000, 0.000, 0.000, 0.000, 0.000, 0.000, 0.000, 0.000, 0.000, 0.000, 0.000, 0.000, 0.000, 0.000], "score": [0.000, 0.000, 0.000, 0.000, 0.000, 0.000, 0.000, 0.000, 0.057, 0.666, 0.149, 0.000, 0.000, 0.000, 0.000, 0.000, 0.000, 0.000]}]}, {"frame_index": 187, "skeleton": [{"pose": [0.000, 0.000, 0.608, 0.359, 0.569, 0.329, 0.540, 0.397, 0.000, 0.000, 0.653, 0.361, 0.000, 0.000, 0.000, 0.000, 0.538, 0.440, 0.483, 0.375, 0.481, 0.511, 0.000, 0.000, 0.000, 0.000, 0.000, 0.000, 0.000, 0.000, 0.000, 0.000, 0.614, 0.367, 0.000, 0.000], "score": [0.000, 0.165, 0.343, 0.114, 0.000, 0.088, 0.000, 0.000, 0.067, 0.606, 0.192, 0.000, 0.000, 0.000, 0.000, 0.000, 0.078, 0.000]}]}, {"frame_index": 188, "skeleton": [{"pose": [0.000, 0.000, 0.612, 0.348, 0.567, 0.323, 0.540, 0.399, 0.000, 0.000, 0.659, 0.356, 0.661, 0.446, 0.647, 0.448, 0.532, 0.446, 0.483, 0.372, 0.479, 0.505, 0.000, 0.000, 0.000, 0.000, 0.000, 0.000, 0.000, 0.000, 0.000, 0.000, 0.614, 0.367, 0.000, 0.000], "score": [0.000, 0.327, 0.420, 0.157, 0.000, 0.260, 0.104, 0.059, 0.141, 0.629, 0.205, 0.000, 0.000, 0.000, 0.000, 0.000, 0.062, 0.000]}]}, {"frame_index": 189, "skeleton": [{"pose": [0.000, 0.000, 0.612, 0.345, 0.573, 0.321, 0.540, 0.391, 0.000, 0.000, 0.653, 0.353, 0.000, 0.000, 0.000, 0.000, 0.538, 0.443, 0.483, 0.370, 0.481, 0.505, 0.000, 0.000, 0.000, 0.000, 0.000, 0.000, 0.000, 0.000, 0.000, 0.000, 0.000, 0.000, 0.000, 0.000], "score": [0.000, 0.232, 0.332, 0.128, 0.000, 0.153, 0.000, 0.000, 0.095, 0.579, 0.209, 0.000, 0.000, 0.000, 0.000, 0.000, 0.000, 0.000]}]}, {"frame_index": 190, "skeleton": [{"pose": [0.000, 0.000, 0.612, 0.356, 0.569, 0.323, 0.534, 0.389, 0.000, 0.000, 0.649, 0.351, 0.000, 0.000, 0.000, 0.000, 0.534, 0.421, 0.483, 0.370, 0.481, 0.514, 0.000, 0.000, 0.000, 0.000, 0.000, 0.000, 0.000, 0.000, 0.000, 0.000, 0.000, 0.000, 0.000, 0.000], "score": [0.000, 0.186, 0.284, 0.101, 0.000, 0.108, 0.000, 0.000, 0.093, 0.594, 0.200, 0.000, 0.000, 0.000, 0.000, 0.000, 0.000, 0.000]}]}, {"frame_index": 191, "skeleton": [{"pose": [0.000, 0.000, 0.612, 0.348, 0.571, 0.321, 0.536, 0.386, 0.534, 0.465, 0.649, 0.351, 0.000, 0.000, 0.000, 0.000, 0.534, 0.429, 0.483, 0.372, 0.481, 0.514, 0.000, 0.000, 0.000, 0.000, 0.000, 0.000, 0.000, 0.000, 0.000, 0.000, 0.000, 0.000, 0.000, 0.000], "score": [0.000, 0.239, 0.359, 0.118, 0.063, 0.180, 0.000, 0.000, 0.120, 0.625, 0.236, 0.000, 0.000, 0.000, 0.000, 0.000, 0.000, 0.000]}]}, {"frame_index": 192, "skeleton": []}, {"frame_index": 193, "skeleton": []}, {"frame_index": 194, "skeleton": []}, {"frame_index": 195, "skeleton": []}, {"frame_index": 196, "skeleton": []}, {"frame_index": 197, "skeleton": []}, {"frame_index": 198, "skeleton": []}, {"frame_index": 199, "skeleton": []}, {"frame_index": 200, "skeleton": []}, {"frame_index": 201, "skeleton": []}, {"frame_index": 202, "skeleton": []}, {"frame_index": 203, "skeleton": []}, {"frame_index": 204, "skeleton": []}, {"frame_index": 205, "skeleton": []}, {"frame_index": 206, "skeleton": []}, {"frame_index": 207, "skeleton": []}, {"frame_index": 208, "skeleton": []}, {"frame_index": 209, "skeleton": [{"pose": [0.000, 0.000, 0.000, 0.000, 0.000, 0.000, 0.000, 0.000, 0.000, 0.000, 0.000, 0.000, 0.000, 0.000, 0.000, 0.000, 0.225, 0.448, 0.219, 0.666, 0.205, 0.856, 0.000, 0.000, 0.000, 0.000, 0.000, 0.000, 0.000, 0.000, 0.000, 0.000, 0.000, 0.000, 0.000, 0.000], "score": [0.000, 0.000, 0.000, 0.000, 0.000, 0.000, 0.000, 0.000, 0.105, 0.226, 0.302, 0.000, 0.000, 0.000, 0.000, 0.000, 0.000, 0.000]}]}, {"frame_index": 210, "skeleton": []}, {"frame_index": 211, "skeleton": []}, {"frame_index": 212, "skeleton": []}, {"frame_index": 213, "skeleton": []}, {"frame_index": 214, "skeleton": [{"pose": [0.000, 0.000, 0.000, 0.000, 0.000, 0.000, 0.000, 0.000, 0.000, 0.000, 0.000, 0.000, 0.000, 0.000, 0.000, 0.000, 0.215, 0.402, 0.221, 0.652, 0.207, 0.864, 0.000, 0.000, 0.000, 0.000, 0.000, 0.000, 0.000, 0.000, 0.000, 0.000, 0.000, 0.000, 0.000, 0.000], "score": [0.000, 0.000, 0.000, 0.000, 0.000, 0.000, 0.000, 0.000, 0.096, 0.243, 0.369, 0.000, 0.000, 0.000, 0.000, 0.000, 0.000, 0.000]}]}, {"frame_index": 215, "skeleton": []}, {"frame_index": 216, "skeleton": []}, {"frame_index": 217, "skeleton": []}, {"frame_index": 218, "skeleton": []}, {"frame_index": 219, "skeleton": []}, {"frame_index": 220, "skeleton": []}, {"frame_index": 221, "skeleton": []}, {"frame_index": 222, "skeleton": []}, {"frame_index": 223, "skeleton": []}, {"frame_index": 224, "skeleton": []}, {"frame_index": 225, "skeleton": []}, {"frame_index": 226, "skeleton": []}, {"frame_index": 227, "skeleton": []}, {"frame_index": 228, "skeleton": []}, {"frame_index": 229, "skeleton": []}, {"frame_index": 230, "skeleton": []}, {"frame_index": 231, "skeleton": [{"pose": [0.000, 0.000, 0.000, 0.000, 0.000, 0.000, 0.000, 0.000, 0.000, 0.000, 0.000, 0.000, 0.000, 0.000, 0.000, 0.000, 0.241, 0.378, 0.227, 0.663, 0.221, 0.875, 0.000, 0.000, 0.000, 0.000, 0.000, 0.000, 0.000, 0.000, 0.000, 0.000, 0.000, 0.000, 0.000, 0.000], "score": [0.000, 0.000, 0.000, 0.000, 0.000, 0.000, 0.000, 0.000, 0.104, 0.225, 0.255, 0.000, 0.000, 0.000, 0.000, 0.000, 0.000, 0.000]}]}, {"frame_index": 232, "skeleton": [{"pose": [0.000, 0.000, 0.225, 0.168, 0.000, 0.000, 0.000, 0.000, 0.000, 0.000, 0.000, 0.000, 0.000, 0.000, 0.000, 0.000, 0.235, 0.451, 0.231, 0.685, 0.223, 0.878, 0.151, 0.443, 0.168, 0.698, 0.156, 0.948, 0.000, 0.000, 0.000, 0.000, 0.000, 0.000, 0.000, 0.000], "score": [0.000, 0.055, 0.000, 0.000, 0.000, 0.000, 0.000, 0.000, 0.190, 0.309, 0.374, 0.187, 0.190, 0.181, 0.000, 0.000, 0.000, 0.000]}, {"pose": [0.886, 0.359, 0.000, 0.000, 0.000, 0.000, 0.000, 0.000, 0.000, 0.000, 0.000, 0.000, 0.000, 0.000, 0.000, 0.000, 0.000, 0.000, 0.000, 0.000, 0.000, 0.000, 0.000, 0.000, 0.000, 0.000, 0.000, 0.000, 0.859, 0.318, 0.908, 0.318, 0.000, 0.000, 0.956, 0.340], "score": [0.259, 0.000, 0.000, 0.000, 0.000, 0.000, 0.000, 0.000, 0.000, 0.000, 0.000, 0.000, 0.000, 0.000, 0.226, 0.321, 0.000, 0.074]}]}, {"frame_index": 233, "skeleton": []}, {"frame_index": 234, "skeleton": [{"pose": [0.000, 0.000, 0.000, 0.000, 0.000, 0.000, 0.000, 0.000, 0.000, 0.000, 0.000, 0.000, 0.000, 0.000, 0.000, 0.000, 0.221, 0.470, 0.233, 0.688, 0.221, 0.878, 0.000, 0.000, 0.000, 0.000, 0.000, 0.000, 0.000, 0.000, 0.000, 0.000, 0.000, 0.000, 0.000, 0.000], "score": [0.000, 0.000, 0.000, 0.000, 0.000, 0.000, 0.000, 0.000, 0.082, 0.208, 0.264, 0.000, 0.000, 0.000, 0.000, 0.000, 0.000, 0.000]}]}, {"frame_index": 235, "skeleton": []}, {"frame_index": 236, "skeleton": [{"pose": [0.000, 0.000, 0.000, 0.000, 0.000, 0.000, 0.000, 0.000, 0.000, 0.000, 0.000, 0.000, 0.000, 0.000, 0.000, 0.000, 0.266, 0.280, 0.227, 0.663, 0.219, 0.875, 0.000, 0.000, 0.000, 0.000, 0.000, 0.000, 0.000, 0.000, 0.000, 0.000, 0.000, 0.000, 0.000, 0.000], "score": [0.000, 0.000, 0.000, 0.000, 0.000, 0.000, 0.000, 0.000, 0.106, 0.258, 0.311, 0.000, 0.000, 0.000, 0.000, 0.000, 0.000, 0.000]}]}, {"frame_index": 237, "skeleton": []}, {"frame_index": 238, "skeleton": []}, {"frame_index": 239, "skeleton": []}, {"frame_index": 240, "skeleton": []}, {"frame_index": 241, "skeleton": [{"pose": [0.000, 0.000, 0.000, 0.000, 0.000, 0.000, 0.000, 0.000, 0.000, 0.000, 0.000, 0.000, 0.000, 0.000, 0.000, 0.000, 0.219, 0.416, 0.235, 0.671, 0.221, 0.861, 0.000, 0.000, 0.000, 0.000, 0.000, 0.000, 0.000, 0.000, 0.000, 0.000, 0.000, 0.000, 0.000, 0.000], "score": [0.000, 0.000, 0.000, 0.000, 0.000, 0.000, 0.000, 0.000, 0.165, 0.378, 0.419, 0.000, 0.000, 0.000, 0.000, 0.000, 0.000, 0.000]}]}, {"frame_index": 242, "skeleton": []}, {"frame_index": 243, "skeleton": []}, {"frame_index": 244, "skeleton": []}, {"frame_index": 245, "skeleton": []}, {"frame_index": 246, "skeleton": []}, {"frame_index": 247, "skeleton": [{"pose": [0.000, 0.000, 0.000, 0.000, 0.000, 0.000, 0.000, 0.000, 0.000, 0.000, 0.000, 0.000, 0.000, 0.000, 0.000, 0.000, 0.252, 0.348, 0.229, 0.666, 0.213, 0.872, 0.000, 0.000, 0.000, 0.000, 0.000, 0.000, 0.000, 0.000, 0.000, 0.000, 0.000, 0.000, 0.000, 0.000], "score": [0.000, 0.000, 0.000, 0.000, 0.000, 0.000, 0.000, 0.000, 0.094, 0.235, 0.259, 0.000, 0.000, 0.000, 0.000, 0.000, 0.000, 0.000]}]}, {"frame_index": 248, "skeleton": [{"pose": [0.000, 0.000, 0.000, 0.000, 0.000, 0.000, 0.000, 0.000, 0.000, 0.000, 0.000, 0.000, 0.000, 0.000, 0.000, 0.000, 0.254, 0.288, 0.225, 0.644, 0.219, 0.867, 0.000, 0.000, 0.000, 0.000, 0.000, 0.000, 0.000, 0.000, 0.000, 0.000, 0.000, 0.000, 0.000, 0.000], "score": [0.000, 0.000, 0.000, 0.000, 0.000, 0.000, 0.000, 0.000, 0.172, 0.223, 0.329, 0.000, 0.000, 0.000, 0.000, 0.000, 0.000, 0.000]}]}, {"frame_index": 249, "skeleton": []}, {"frame_index": 250, "skeleton": []}, {"frame_index": 251, "skeleton": [{"pose": [0.000, 0.000, 0.000, 0.000, 0.000, 0.000, 0.000, 0.000, 0.000, 0.000, 0.000, 0.000, 0.000, 0.000, 0.000, 0.000, 0.237, 0.337, 0.235, 0.660, 0.221, 0.861, 0.000, 0.000, 0.000, 0.000, 0.000, 0.000, 0.000, 0.000, 0.000, 0.000, 0.000, 0.000, 0.000, 0.000], "score": [0.000, 0.000, 0.000, 0.000, 0.000, 0.000, 0.000, 0.000, 0.157, 0.367, 0.381, 0.000, 0.000, 0.000, 0.000, 0.000, 0.000, 0.000]}]}, {"frame_index": 252, "skeleton": [{"pose": [0.000, 0.000, 0.000, 0.000, 0.000, 0.000, 0.000, 0.000, 0.000, 0.000, 0.000, 0.000, 0.000, 0.000, 0.000, 0.000, 0.237, 0.418, 0.235, 0.671, 0.219, 0.875, 0.000, 0.000, 0.000, 0.000, 0.000, 0.000, 0.000, 0.000, 0.000, 0.000, 0.000, 0.000, 0.000, 0.000], "score": [0.000, 0.000, 0.000, 0.000, 0.000, 0.000, 0.000, 0.000, 0.138, 0.395, 0.360, 0.000, 0.000, 0.000, 0.000, 0.000, 0.000, 0.000]}]}, {"frame_index": 253, "skeleton": []}, {"frame_index": 254, "skeleton": []}, {"frame_index": 255, "skeleton": [{"pose": [0.000, 0.000, 0.000, 0.000, 0.000, 0.000, 0.000, 0.000, 0.000, 0.000, 0.000, 0.000, 0.000, 0.000, 0.000, 0.000, 0.223, 0.391, 0.223, 0.674, 0.209, 0.875, 0.000, 0.000, 0.000, 0.000, 0.000, 0.000, 0.000, 0.000, 0.000, 0.000, 0.000, 0.000, 0.000, 0.000], "score": [0.000, 0.000, 0.000, 0.000, 0.000, 0.000, 0.000, 0.000, 0.097, 0.294, 0.382, 0.000, 0.000, 0.000, 0.000, 0.000, 0.000, 0.000]}]}, {"frame_index": 256, "skeleton": [{"pose": [0.000, 0.000, 0.000, 0.000, 0.000, 0.000, 0.000, 0.000, 0.000, 0.000, 0.000, 0.000, 0.000, 0.000, 0.000, 0.000, 0.221, 0.399, 0.221, 0.668, 0.207, 0.878, 0.000, 0.000, 0.000, 0.000, 0.000, 0.000, 0.000, 0.000, 0.000, 0.000, 0.000, 0.000, 0.000, 0.000], "score": [0.000, 0.000, 0.000, 0.000, 0.000, 0.000, 0.000, 0.000, 0.096, 0.226, 0.292, 0.000, 0.000, 0.000, 0.000, 0.000, 0.000, 0.000]}]}, {"frame_index": 257, "skeleton": []}, {"frame_index": 258, "skeleton": []}, {"frame_index": 259, "skeleton": []}, {"frame_index": 260, "skeleton": []}, {"frame_index": 261, "skeleton": []}, {"frame_index": 262, "skeleton": [{"pose": [0.000, 0.000, 0.000, 0.000, 0.000, 0.000, 0.000, 0.000, 0.000, 0.000, 0.000, 0.000, 0.000, 0.000, 0.000, 0.000, 0.227, 0.418, 0.233, 0.671, 0.221, 0.872, 0.000, 0.000, 0.000, 0.000, 0.000, 0.000, 0.000, 0.000, 0.000, 0.000, 0.000, 0.000, 0.000, 0.000], "score": [0.000, 0.000, 0.000, 0.000, 0.000, 0.000, 0.000, 0.000, 0.113, 0.336, 0.378, 0.000, 0.000, 0.000, 0.000, 0.000, 0.000, 0.000]}]}, {"frame_index": 263, "skeleton": []}, {"frame_index": 264, "skeleton": []}, {"frame_index": 265, "skeleton": []}, {"frame_index": 266, "skeleton": []}, {"frame_index": 267, "skeleton": []}, {"frame_index": 268, "skeleton": []}, {"frame_index": 269, "skeleton": []}, {"frame_index": 270, "skeleton": []}, {"frame_index": 271, "skeleton": []}, {"frame_index": 272, "skeleton": [{"pose": [0.000, 0.000, 0.000, 0.000, 0.000, 0.000, 0.000, 0.000, 0.000, 0.000, 0.000, 0.000, 0.000, 0.000, 0.000, 0.000, 0.233, 0.440, 0.237, 0.679, 0.223, 0.867, 0.000, 0.000, 0.000, 0.000, 0.000, 0.000, 0.000, 0.000, 0.000, 0.000, 0.000, 0.000, 0.000, 0.000], "score": [0.000, 0.000, 0.000, 0.000, 0.000, 0.000, 0.000, 0.000, 0.241, 0.484, 0.555, 0.000, 0.000, 0.000, 0.000, 0.000, 0.000, 0.000]}]}, {"frame_index": 273, "skeleton": []}, {"frame_index": 274, "skeleton": []}, {"frame_index": 275, "skeleton": []}, {"frame_index": 276, "skeleton": [{"pose": [0.000, 0.000, 0.000, 0.000, 0.000, 0.000, 0.000, 0.000, 0.000, 0.000, 0.000, 0.000, 0.000, 0.000, 0.000, 0.000, 0.233, 0.421, 0.239, 0.669, 0.223, 0.859, 0.000, 0.000, 0.000, 0.000, 0.000, 0.000, 0.000, 0.000, 0.000, 0.000, 0.000, 0.000, 0.000, 0.000], "score": [0.000, 0.000, 0.000, 0.000, 0.000, 0.000, 0.000, 0.000, 0.120, 0.390, 0.487, 0.000, 0.000, 0.000, 0.000, 0.000, 0.000, 0.000]}]}, {"frame_index": 277, "skeleton": [{"pose": [0.000, 0.000, 0.000, 0.000, 0.000, 0.000, 0.000, 0.000, 0.000, 0.000, 0.000, 0.000, 0.000, 0.000, 0.000, 0.000, 0.237, 0.394, 0.243, 0.658, 0.225, 0.856, 0.000, 0.000, 0.000, 0.000, 0.000, 0.000, 0.000, 0.000, 0.000, 0.000, 0.000, 0.000, 0.000, 0.000], "score": [0.000, 0.000, 0.000, 0.000, 0.000, 0.000, 0.000, 0.000, 0.074, 0.319, 0.388, 0.000, 0.000, 0.000, 0.000, 0.000, 0.000, 0.000]}]}, {"frame_index": 278, "skeleton": []}, {"frame_index": 279, "skeleton": []}, {"frame_index": 280, "skeleton": []}, {"frame_index": 281, "skeleton": [{"pose": [0.000, 0.000, 0.000, 0.000, 0.000, 0.000, 0.000, 0.000, 0.000, 0.000, 0.000, 0.000, 0.000, 0.000, 0.000, 0.000, 0.205, 0.356, 0.248, 0.649, 0.237, 0.856, 0.000, 0.000, 0.000, 0.000, 0.000, 0.000, 0.000, 0.000, 0.000, 0.000, 0.000, 0.000, 0.000, 0.000], "score": [0.000, 0.000, 0.000, 0.000, 0.000, 0.000, 0.000, 0.000, 0.061, 0.219, 0.451, 0.000, 0.000, 0.000, 0.000, 0.000, 0.000, 0.000]}]}, {"frame_index": 282, "skeleton": [{"pose": [0.000, 0.000, 0.000, 0.000, 0.000, 0.000, 0.000, 0.000, 0.000, 0.000, 0.000, 0.000, 0.000, 0.000, 0.000, 0.000, 0.252, 0.476, 0.252, 0.696, 0.237, 0.861, 0.000, 0.000, 0.000, 0.000, 0.000, 0.000, 0.000, 0.000, 0.000, 0.000, 0.000, 0.000, 0.000, 0.000], "score": [0.000, 0.000, 0.000, 0.000, 0.000, 0.000, 0.000, 0.000, 0.230, 0.332, 0.493, 0.000, 0.000, 0.000, 0.000, 0.000, 0.000, 0.000]}]}, {"frame_index": 283, "skeleton": []}, {"frame_index": 284, "skeleton": []}, {"frame_index": 285, "skeleton": []}, {"frame_index": 286, "skeleton": []}, {"frame_index": 287, "skeleton": [{"pose": [0.000, 0.000, 0.000, 0.000, 0.000, 0.000, 0.000, 0.000, 0.000, 0.000, 0.000, 0.000, 0.000, 0.000, 0.000, 0.000, 0.227, 0.443, 0.252, 0.668, 0.237, 0.859, 0.000, 0.000, 0.000, 0.000, 0.000, 0.000, 0.000, 0.000, 0.000, 0.000, 0.000, 0.000, 0.000, 0.000], "score": [0.000, 0.000, 0.000, 0.000, 0.000, 0.000, 0.000, 0.000, 0.091, 0.216, 0.311, 0.000, 0.000, 0.000, 0.000, 0.000, 0.000, 0.000]}]}, {"frame_index": 288, "skeleton": [{"pose": [0.000, 0.000, 0.000, 0.000, 0.000, 0.000, 0.000, 0.000, 0.000, 0.000, 0.000, 0.000, 0.000, 0.000, 0.000, 0.000, 0.190, 0.226, 0.258, 0.660, 0.237, 0.856, 0.000, 0.000, 0.000, 0.000, 0.000, 0.000, 0.000, 0.000, 0.000, 0.000, 0.000, 0.000, 0.000, 0.000], "score": [0.000, 0.000, 0.000, 0.000, 0.000, 0.000, 0.000, 0.000, 0.062, 0.257, 0.458, 0.000, 0.000, 0.000, 0.000, 0.000, 0.000, 0.000]}]}, {"frame_index": 289, "skeleton": []}, {"frame_index": 290, "skeleton": []}, {"frame_index": 291, "skeleton": []}, {"frame_index": 292, "skeleton": []}, {"frame_index": 293, "skeleton": []}, {"frame_index": 294, "skeleton": []}, {"frame_index": 295, "skeleton": [{"pose": [0.485, 0.356, 0.544, 0.489, 0.479, 0.522, 0.000, 0.000, 0.000, 0.000, 0.604, 0.457, 0.681, 0.511, 0.726, 0.682, 0.546, 0.674, 0.000, 0.000, 0.000, 0.000, 0.647, 0.658, 0.000, 0.000, 0.000, 0.000, 0.000, 0.000, 0.000, 0.000, 0.000, 0.000, 0.000, 0.000], "score": [0.055, 0.187, 0.110, 0.000, 0.000, 0.212, 0.515, 0.390, 0.052, 0.000, 0.000, 0.055, 0.000, 0.000, 0.000, 0.000, 0.000, 0.000]}, {"pose": [0.000, 0.000, 0.000, 0.000, 0.186, 0.313, 0.301, 0.470, 0.325, 0.364, 0.000, 0.000, 0.000, 0.000, 0.000, 0.000, 0.000, 0.000, 0.000, 0.000, 0.000, 0.000, 0.000, 0.000, 0.000, 0.000, 0.000, 0.000, 0.000, 0.000, 0.000, 0.000, 0.000, 0.000, 0.000, 0.000], "score": [0.000, 0.000, 0.147, 0.414, 0.230, 0.000, 0.000, 0.000, 0.000, 0.000, 0.000, 0.000, 0.000, 0.000, 0.000, 0.000, 0.000, 0.000]}]}, {"frame_index": 296, "skeleton": [{"pose": [0.469, 0.421, 0.544, 0.492, 0.481, 0.530, 0.000, 0.000, 0.000, 0.000, 0.606, 0.462, 0.681, 0.511, 0.726, 0.682, 0.000, 0.000, 0.000, 0.000, 0.000, 0.000, 0.000, 0.000, 0.000, 0.000, 0.000, 0.000, 0.000, 0.000, 0.000, 0.000, 0.000, 0.000, 0.000, 0.000], "score": [0.067, 0.204, 0.112, 0.000, 0.000, 0.256, 0.508, 0.407, 0.000, 0.000, 0.000, 0.000, 0.000, 0.000, 0.000, 0.000, 0.000, 0.000]}]}, {"frame_index": 297, "skeleton": []}, {"frame_index": 298, "skeleton": [{"pose": [0.471, 0.397, 0.530, 0.489, 0.450, 0.508, 0.000, 0.000, 0.000, 0.000, 0.593, 0.459, 0.681, 0.511, 0.718, 0.668, 0.000, 0.000, 0.000, 0.000, 0.000, 0.000, 0.000, 0.000, 0.000, 0.000, 0.000, 0.000, 0.464, 0.356, 0.495, 0.356, 0.432, 0.383, 0.000, 0.000], "score": [0.072, 0.174, 0.093, 0.000, 0.000, 0.219, 0.526, 0.346, 0.000, 0.000, 0.000, 0.000, 0.000, 0.000, 0.122, 0.065, 0.112, 0.000]}]}, {"frame_index": 299, "skeleton": [{"pose": [0.475, 0.389, 0.532, 0.489, 0.450, 0.514, 0.000, 0.000, 0.000, 0.000, 0.595, 0.459, 0.681, 0.511, 0.714, 0.663, 0.538, 0.696, 0.000, 0.000, 0.000, 0.000, 0.649, 0.663, 0.000, 0.000, 0.000, 0.000, 0.462, 0.356, 0.495, 0.345, 0.000, 0.000, 0.000, 0.000], "score": [0.066, 0.189, 0.092, 0.000, 0.000, 0.223, 0.520, 0.343, 0.050, 0.000, 0.000, 0.058, 0.000, 0.000, 0.119, 0.069, 0.000, 0.000]}]}], "label": "filling eyebrows", "label_index": 126}